Workbook

Sheet Petunjuk
A1: LEADERSHIP THAT WORKS — Facilitator & Participant Toolkit
A2: Lead Yourself. Think Better. Decide Smarter. Execute Stronger.
A3: Sel kuning (teks biru) = input. Sel lain = rumus/panduan, jangan ditimpa. Nama bank, tanggal, dan trainer silakan disesuaikan.
A5: Sheet | B5: Judul | C5: Fungsi / cara pakai
A6: 1 Self-Diagnostic | B6: Leadership Self-Diagnostic (Pre & Post) | C6: Isi skor 1–5 sebelum training (Pre) dan di akhir Day 2 (Post). Grafik radar terbarui otomatis.
A7: 2 480-Minute | B7: Game 2 · The 480-Minute Challenge (Time Audit) | C7: Isi 1 pada kolom Pilih untuk aktivitas yang 'dibeli'. Kolom poin (konsekuensi tersembunyi) disembunyikan dari peserta saat bermain — sembunyikan kolom G–L bila diproyeksikan.
A8: 3 Priority Scorecard | B8: Priority Matrix & Banking Priority Scorecard | C8: Skor 1–5 untuk 6 dimensi. Skor tertimbang → P1–P4 otomatis. Override: Risk atau Compliance = 5 → P1.
A9: 4 Weekly Planner | B9: Weekly Leadership Planner & Time Blocking | C9: Pilih kategori di setiap slot 30 menit. Sistem menghitung % buffer (target 15–20%) dan % focus.
A10: 5 Big3 & Meeting | B10: Daily Big 3 & Meeting Checklist | C10: Tulis 3 hasil (outcome) setiap pagi sebelum membuka email. Tandai Y bila selesai.
A11: 6 Delegation | B11: Delegation Contract, Level Guide & RACI | C11: Isi satu kolom per delegasi. Sistem memeriksa kelengkapan 8 elemen.
A12: 7 GROW & SBI | B12: GROW Coaching Sheet & SBI Feedback Card | C12: Leader bertanya, staf menjawab. SBI menyusun kalimat feedback otomatis.
A13: 8 Fact-Assumption | B13: Fact-Assumption-Opinion Sheet & Critical Thinking Questions | C13: Klasifikasikan setiap pernyataan sebelum menyimpulkan.
A14: 9 Root Cause | B14: 5 Whys, Fishbone & Issue Tree | C14: Gunakan fishbone untuk memetakan penyebab, 5 Whys untuk menggali kandidat terkuat, issue tree untuk memecah masalah.
A15: 10 Bias Checklist | B15: Bias Checklist sebelum memutuskan | C15: Jawab Y bila tanda bias terdeteksi; tuliskan mitigasi.
A16: 11 Decision Matrix | B16: Decision Matrix (9 kriteria) | C16: Skor 1–5 (5 = paling menguntungkan). Untuk Risk & Execution Difficulty: risiko rendah / mudah = skor tinggi.
... A31: 25 Evaluasi Training | B31: Training Effectiveness Measurement · Kirkpatrick L1–L4 | C31: Ringkasan bukti efektivitas training. L1 diisi akhir Day 2; L2 dari test; L3 dari follow-up D30; L4 dari impact metrics.
A33: Pemetaan 25 tools | C33: 1 Self-Diagnostic · 2 480-Minute Audit · 3 Priority Matrix & Scorecard · 4 Weekly Planner/Time Blocking · 5 Daily Big 3 & Meeting Checklist · 6 Delegation Contract, Level Guide & RACI · 7 GROW & SBI · 8 Fact-Assumption & Questions Card · 9 5 Whys, Fishbone, Issue Tree · 10 Bias Checklist · 11 Decision Matrix · 12 Pre-Mortem · 13 Decision Log · 14 Action Tracker · 23 AAR & Stop-Start-Continue · 20 30-Day Plan

Sheet 1 Self-Diagnostic
A1: Leadership Self-Diagnostic (Pre & Post)
A2: Isi skor 1–5 sebelum training (Pre) dan di akhir Day 2 (Post). Grafik radar terbarui otomatis.
A3: Legenda: sel kuning = diisi peserta/trainer (teks biru); sel putih/abu = otomatis (rumus) atau panduan.
A5: Dimensi | B5: Pre (1–5) | C5: Post (1–5) | D5: Gap | E5: Status | F5: Catatan / contoh perilaku
A6: Priority Management | B6: 3 | C6: 4 | D6: =IF(OR(B6="",C6=""),"",C6-B6) -> 1 | E6: =IF(B6="","",IF(B6<=2,"Prioritas pengembangan",IF(B6=3,"Cukup, perlu konsistensi","Kekuatan"))) -> Cukup, perlu konsistensi | F6: Contoh: sering mengerjakan permintaan sesuai urutan datang
A7: Time Management | D7: =IF(OR(B7="",C7=""),"",C7-B7) | E7: =IF(B7="","",IF(B7<=2,"Prioritas pengembangan",IF(B7=3,"Cukup, perlu konsistensi","Kekuatan")))
A8: Focus | D8: =IF(OR(B8="",C8=""),"",C8-B8) | E8: =IF(B8="","",IF(B8<=2,"Prioritas pengembangan",IF(B8=3,"Cukup, perlu konsistensi","Kekuatan")))
A9: Delegation | D9: =IF(OR(B9="",C9=""),"",C9-B9) | E9: =IF(B9="","",IF(B9<=2,"Prioritas pengembangan",IF(B9=3,"Cukup, perlu konsistensi","Kekuatan")))
A10: Critical Thinking | D10: =IF(OR(B10="",C10=""),"",C10-B10) | E10: =IF(B10="","",IF(B10<=2,"Prioritas pengembangan",IF(B10=3,"Cukup, perlu konsistensi","Kekuatan")))
A11: Decision Making | D11: =IF(OR(B11="",C11=""),"",C11-B11) | E11: =IF(B11="","",IF(B11<=2,"Prioritas pengembangan",IF(B11=3,"Cukup, perlu konsistensi","Kekuatan")))
A12: Communication | D12: =IF(OR(B12="",C12=""),"",C12-B12) | E12: =IF(B12="","",IF(B12<=2,"Prioritas pengembangan",IF(B12=3,"Cukup, perlu konsistensi","Kekuatan")))
A13: Accountability | D13: =IF(OR(B13="",C13=""),"",C13-B13) | E13: =IF(B13="","",IF(B13<=2,"Prioritas pengembangan",IF(B13=3,"Cukup, perlu konsistensi","Kekuatan")))
A14: Coaching | D14: =IF(OR(B14="",C14=""),"",C14-B14) | E14: =IF(B14="","",IF(B14<=2,"Prioritas pengembangan",IF(B14=3,"Cukup, perlu konsistensi","Kekuatan")))
A15: Execution | D15: =IF(OR(B15="",C15=""),"",C15-B15) | E15: =IF(B15="","",IF(B15<=2,"Prioritas pengembangan",IF(B15=3,"Cukup, perlu konsistensi","Kekuatan")))
A16: Rata-rata | B16: =IFERROR(AVERAGE(B6:B15),"") -> 3 | C16: =IFERROR(AVERAGE(C6:C15),"") -> 4 | D16: =IFERROR(C16-B16,"") -> 1
A18: Apa satu masalah leadership terbesar yang saat ini mengganggu efektivitas kerja Anda?
A21: Bawa 4 contoh nyata (dipakai anonim)
A22: 1 contoh keputusan sulit
A23: 1 contoh pekerjaan yang sering overdue
A24: 1 contoh situasi terlalu banyak prioritas
A25: 1 contoh masalah tim

Sheet 2 480-Minute
A1: Game 2 · The 480-Minute Challenge (Time Audit)
A2: Isi 1 pada kolom Pilih untuk aktivitas yang 'dibeli'. Kolom poin (konsekuensi tersembunyi) disembunyikan dari peserta saat bermain — sembunyikan kolom G–L bila diproyeksikan.
A3: Legenda: sel kuning = diisi peserta/trainer (teks biru); sel putih/abu = otomatis (rumus) atau panduan.
A5: Aktivitas | B5: Menit | C5: Kategori | D5: Pilih (1/0) | E5: Menit terpakai | F5: Risk critical? | G5: Business | H5: Customer | I5: Risk | J5: People | K5: Execution | L5: Penalti | M5: Catatan
A6: Customer complaint | B6: 45 | C6: Urgent+Important | E6: =B6*N(D6) -> 0 | F6: N | G6: 1 | H6: 5 | I6: 2 | J6: 0 | K6: 1 | L6: =IF(AND(F6="Y",N(D6)=0),-10,0) -> 0
A7: Business target review | B7: 60 | C7: Important | E7: =B7*N(D7) -> 0 | F7: N | G7: 5 | H7: 1 | I7: 0 | J7: 1 | K7: 2 | L7: =IF(AND(F7="Y",N(D7)=0),-10,0) -> 0
A8: Routine meeting | B8: 60 | C8: Urgent | E8: =B8*N(D8) -> 0 | F8: N | G8: 1 | H8: 0 | I8: 0 | J8: 1 | K8: 1 | L8: =IF(AND(F8="Y",N(D8)=0),-10,0) -> 0
A9: Regulatory deadline | B9: 90 | C9: Urgent+Important | E9: =B9*N(D9) -> 0 | F9: Y | G9: 1 | H9: 0 | I9: 5 | J9: 0 | K9: 2 | L9: =IF(AND(F9="Y",N(D9)=0),-10,0) -> -10
A10: Employee coaching | B10: 45 | C10: Important | E10: =B10*N(D10) -> 0 | F10: N | G10: 1 | H10: 1 | I10: 0 | J10: 5 | K10: 1 | L10: =IF(AND(F10="Y",N(D10)=0),-10,0) -> 0
A11: Credit approval | B11: 60 | C11: Urgent+Important | E11: =B11*N(D11) -> 0 | F11: N | G11: 4 | H11: 3 | I11: 2 | J11: 0 | K11: 2 | L11: =IF(AND(F11="Y",N(D11)=0),-10,0) -> 0
A12: WhatsApp group | B12: 40 | C12: Neither | E12: =B12*N(D12) -> 0 | F12: N | G12: 0 | H12: 0 | I12: 0 | J12: 1 | K12: 0 | L12: =IF(AND(F12="Y",N(D12)=0),-10,0) -> 0
A13: Fraud alert | B13: 45 | C13: Urgent+Important | E13: =B13*N(D13) -> 0 | F13: Y | G13: 0 | H13: 2 | I13: 5 | J13: 0 | K13: 1 | L13: =IF(AND(F13="Y",N(D13)=0),-10,0) -> -10
A14: Audit finding | B14: 60 | C14: Important | E14: =B14*N(D14) -> 0 | F14: Y | G14: 0 | H14: 0 | I14: 4 | J14: 0 | K14: 2 | L14: =IF(AND(F14="Y",N(D14)=0),-10,0) -> -10
A15: Management request | B15: 45 | C15: Urgent | E15: =B15*N(D15) -> 0 | F15: N | G15: 1 | H15: 0 | I15: 1 | J15: 0 | K15: 2 | L15: =IF(AND(F15="Y",N(D15)=0),-10,0) -> 0
A16: Lunch | B16: 60 | C16: Important | E16: =B16*N(D16) -> 0 | F16: N | G16: 0 | H16: 0 | I16: 0 | J16: 2 | K16: 2 | L16: =IF(AND(F16="Y",N(D16)=0),-10,0) -> 0
A17: Planning | B17: 30 | C17: Important | E17: =B17*N(D17) -> 0 | F17: N | G17: 2 | H17: 1 | I17: 1 | J17: 1 | K17: 4 | L17: =IF(AND(F17="Y",N(D17)=0),-10,0) -> 0
... A25: Learning time | B25: 30 | C25: Important | E25: =B25*N(D25) -> 0 | F25: N | G25: 1 | H25: 0 | I25: 0 | J25: 2 | K25: 1 | L25: =IF(AND(F25="Y",N(D25)=0),-10,0) -> 0
A27: Total menit terpakai | B27: =SUM(E6:E25) -> 0
A28: Sisa menit (dari 480) | B28: =480-B27 -> 480
A29: Status | B29: =IF(B27>480,"MELEBIHI 480 MENIT — kurangi aktivitas","OK") -> OK
A30: % waktu Urgent+Important | B30: =IFERROR(SUMIFS(E6:E25,C6:C25,"Urgent+Important")/B27,0) -> 0
A31: % waktu Important (not urgent) | B31: =IFERROR(SUMIFS(E6:E25,C6:C25,"Important")/B27,0) -> 0
A32: % waktu Urgent (not important) | B32: =IFERROR(SUMIFS(E6:E25,C6:C25,"Urgent")/B27,0) -> 0
A33: % waktu Neither | B33: =IFERROR(SUMIFS(E6:E25,C6:C25,"Neither")/B27,0) -> 0
A35: Skor konsekuensi (dibuka saat debrief)
A36: Dimensi | B36: Skor
A37: Business | B37: =SUMPRODUCT(G6:G25,--(D6:D25=1)) -> 0
A38: Customer | B38: =SUMPRODUCT(H6:H25,--(D6:D25=1)) -> 0
A39: Risk | B39: =SUMPRODUCT(I6:I25,--(D6:D25=1)) -> 0
A40: People | B40: =SUMPRODUCT(J6:J25,--(D6:D25=1)) -> 0
A41: Execution | B41: =SUMPRODUCT(K6:K25,--(D6:D25=1)) -> 0
A42: Penalti risk critical diabaikan | B42: =SUM(L6:L25) -> -30
A43: Penalti melebihi 480 menit | B43: =IF(B27>480,-15,0) -> 0
A44: TOTAL SKOR | B44: =SUM(B37:B43) -> -30
A45: Catatan: biaya menit & poin adalah parameter game (bisa diubah trainer).

Sheet 3 Priority Scorecard
A1: Priority Matrix & Banking Priority Scorecard
A2: Skor 1–5 untuk 6 dimensi. Skor tertimbang → P1–P4 otomatis. Override: Risk atau Compliance = 5 → P1.
A3: Legenda: sel kuning = diisi peserta/trainer (teks biru); sel putih/abu = otomatis (rumus) atau panduan.
A5: Bobot (ubah bila perlu) → | B5: Total bobot harus 100% | C5: 0.2 | D5: 0.15 | E5: 0.2 | F5: 0.2 | G5: 0.15 | H5: 0.1 | I5: =SUM(C5:H5) -> 1
A6: Pekerjaan / permintaan | B6: What happens if I do not do this today? | C6: Urgency | D6: Business | E6: Customer | F6: Risk | G6: Compliance | H6: Strategic | I6: Skor tertimbang | J6: Level | K6: Tindakan (Eisenhower)
A7: Laporan ke regulator (tenggat hari ini) | B7: Sanksi dan temuan kepatuhan | C7: 5 | D7: 2 | E7: 1 | F7: 4 | G7: 5 | H7: 2 | I7: =IF(COUNT(C7:H7)<6,"",SUMPRODUCT(C7:H7,$C$5:$H$5)/$I$5) -> 3.25 | J7: =IF(I7="","",IF(OR(F7=5,G7=5,I7>=4),"P1",IF(I7>=3,"P2",IF(I7>=2,"P3","P4")))) -> P1 | K7: =IF(J7="","",IF(J7="P1","DO / eskalasi hari ini",IF(J7="P2","PLAN: time block minggu ini",IF(J7="P3","DELEGATE dengan contract","ELIMINATE / batch")))) -> DO / eskalasi hari ini
I8: =IF(COUNT(C8:H8)<6,"",SUMPRODUCT(C8:H8,$C$5:$H$5)/$I$5) | J8: =IF(I8="","",IF(OR(F8=5,G8=5,I8>=4),"P1",IF(I8>=3,"P2",IF(I8>=2,"P3","P4")))) | K8: =IF(J8="","",IF(J8="P1","DO / eskalasi hari ini",IF(J8="P2","PLAN: time block minggu ini",IF(J8="P3","DELEGATE dengan contract","ELIMINATE / batch"))))
I9: =IF(COUNT(C9:H9)<6,"",SUMPRODUCT(C9:H9,$C$5:$H$5)/$I$5) | J9: =IF(I9="","",IF(OR(F9=5,G9=5,I9>=4),"P1",IF(I9>=3,"P2",IF(I9>=2,"P3","P4")))) | K9: =IF(J9="","",IF(J9="P1","DO / eskalasi hari ini",IF(J9="P2","PLAN: time block minggu ini",IF(J9="P3","DELEGATE dengan contract","ELIMINATE / batch"))))
I10: =IF(COUNT(C10:H10)<6,"",SUMPRODUCT(C10:H10,$C$5:$H$5)/$I$5) | J10: =IF(I10="","",IF(OR(F10=5,G10=5,I10>=4),"P1",IF(I10>=3,"P2",IF(I10>=2,"P3","P4")))) | K10: =IF(J10="","",IF(J10="P1","DO / eskalasi hari ini",IF(J10="P2","PLAN: time block minggu ini",IF(J10="P3","DELEGATE dengan contract","ELIMINATE / batch"))))
I11: =IF(COUNT(C11:H11)<6,"",SUMPRODUCT(C11:H11,$C$5:$H$5)/$I$5) | J11: =IF(I11="","",IF(OR(F11=5,G11=5,I11>=4),"P1",IF(I11>=3,"P2",IF(I11>=2,"P3","P4")))) | K11: =IF(J11="","",IF(J11="P1","DO / eskalasi hari ini",IF(J11="P2","PLAN: time block minggu ini",IF(J11="P3","DELEGATE dengan contract","ELIMINATE / batch"))))
I12: =IF(COUNT(C12:H12)<6,"",SUMPRODUCT(C12:H12,$C$5:$H$5)/$I$5) | J12: =IF(I12="","",IF(OR(F12=5,G12=5,I12>=4),"P1",IF(I12>=3,"P2",IF(I12>=2,"P3","P4")))) | K12: =IF(J12="","",IF(J12="P1","DO / eskalasi hari ini",IF(J12="P2","PLAN: time block minggu ini",IF(J12="P3","DELEGATE dengan contract","ELIMINATE / batch"))))
I13: =IF(COUNT(C13:H13)<6,"",SUMPRODUCT(C13:H13,$C$5:$H$5)/$I$5) | J13: =IF(I13="","",IF(OR(F13=5,G13=5,I13>=4),"P1",IF(I13>=3,"P2",IF(I13>=2,"P3","P4")))) | K13: =IF(J13="","",IF(J13="P1","DO / eskalasi hari ini",IF(J13="P2","PLAN: time block minggu ini",IF(J13="P3","DELEGATE dengan contract","ELIMINATE / batch"))))
I14: =IF(COUNT(C14:H14)<6,"",SUMPRODUCT(C14:H14,$C$5:$H$5)/$I$5) | J14: =IF(I14="","",IF(OR(F14=5,G14=5,I14>=4),"P1",IF(I14>=3,"P2",IF(I14>=2,"P3","P4")))) | K14: =IF(J14="","",IF(J14="P1","DO / eskalasi hari ini",IF(J14="P2","PLAN: time block minggu ini",IF(J14="P3","DELEGATE dengan contract","ELIMINATE / batch"))))
I15: =IF(COUNT(C15:H15)<6,"",SUMPRODUCT(C15:H15,$C$5:$H$5)/$I$5) | J15: =IF(I15="","",IF(OR(F15=5,G15=5,I15>=4),"P1",IF(I15>=3,"P2",IF(I15>=2,"P3","P4")))) | K15: =IF(J15="","",IF(J15="P1","DO / eskalasi hari ini",IF(J15="P2","PLAN: time block minggu ini",IF(J15="P3","DELEGATE dengan contract","ELIMINATE / batch"))))
I16: =IF(COUNT(C16:H16)<6,"",SUMPRODUCT(C16:H16,$C$5:$H$5)/$I$5) | J16: =IF(I16="","",IF(OR(F16=5,G16=5,I16>=4),"P1",IF(I16>=3,"P2",IF(I16>=2,"P3","P4")))) | K16: =IF(J16="","",IF(J16="P1","DO / eskalasi hari ini",IF(J16="P2","PLAN: time block minggu ini",IF(J16="P3","DELEGATE dengan contract","ELIMINATE / batch"))))
I17: =IF(COUNT(C17:H17)<6,"",SUMPRODUCT(C17:H17,$C$5:$H$5)/$I$5) | J17: =IF(I17="","",IF(OR(F17=5,G17=5,I17>=4),"P1",IF(I17>=3,"P2",IF(I17>=2,"P3","P4")))) | K17: =IF(J17="","",IF(J17="P1","DO / eskalasi hari ini",IF(J17="P2","PLAN: time block minggu ini",IF(J17="P3","DELEGATE dengan contract","ELIMINATE / batch"))))
I18: =IF(COUNT(C18:H18)<6,"",SUMPRODUCT(C18:H18,$C$5:$H$5)/$I$5) | J18: =IF(I18="","",IF(OR(F18=5,G18=5,I18>=4),"P1",IF(I18>=3,"P2",IF(I18>=2,"P3","P4")))) | K18: =IF(J18="","",IF(J18="P1","DO / eskalasi hari ini",IF(J18="P2","PLAN: time block minggu ini",IF(J18="P3","DELEGATE dengan contract","ELIMINATE / batch"))))
I19: =IF(COUNT(C19:H19)<6,"",SUMPRODUCT(C19:H19,$C$5:$H$5)/$I$5) | J19: =IF(I19="","",IF(OR(F19=5,G19=5,I19>=4),"P1",IF(I19>=3,"P2",IF(I19>=2,"P3","P4")))) | K19: =IF(J19="","",IF(J19="P1","DO / eskalasi hari ini",IF(J19="P2","PLAN: time block minggu ini",IF(J19="P3","DELEGATE dengan contract","ELIMINATE / batch"))))
... I21: =IF(COUNT(C21:H21)<6,"",SUMPRODUCT(C21:H21,$C$5:$H$5)/$I$5) | J21: =IF(I21="","",IF(OR(F21=5,G21=5,I21>=4),"P1",IF(I21>=3,"P2",IF(I21>=2,"P3","P4")))) | K21: =IF(J21="","",IF(J21="P1","DO / eskalasi hari ini",IF(J21="P2","PLAN: time block minggu ini",IF(J21="P3","DELEGATE dengan contract","ELIMINATE / batch"))))
A23: Panduan level
A24: Level | B24: Aturan | C24: Tindakan
A25: P1 | B25: Skor ≥ 4,0 atau Risk/Compliance = 5 | C25: Kerjakan atau eskalasi hari ini
A26: P2 | B26: Skor 3,0–3,9 | C26: Jadwalkan di time block minggu ini
A27: P3 | B27: Skor 2,0–2,9 | C27: Delegasikan (Delegation Contract)
A28: P4 | B28: Skor < 2,0 | C28: Hapus, gabungkan, batch

Sheet 4 Weekly Planner
A1: Weekly Leadership Planner & Time Blocking
A2: Pilih kategori di setiap slot 30 menit. Sistem menghitung % buffer (target 15–20%) dan % focus.
A3: Legenda: sel kuning = diisi peserta/trainer (teks biru); sel putih/abu = otomatis (rumus) atau panduan.
A5: Jam | B5: Senin | C5: Selasa | D5: Rabu | E5: Kamis | F5: Jumat | H5: Kategori | I5: Jam | J5: % kerja
A6: 08:00 | B6: Admin/Batch | H6: Focus | I6: =COUNTIF($B$6:$F$23,H6)*0.5 -> 2 | J6: =IF(H6="Break","",IFERROR(I6/(SUM($I$6:$I$12)-$I$12),0)) -> 0.25
A7: 08:30 | B7: Focus | H7: Meeting | I7: =COUNTIF($B$6:$F$23,H7)*0.5 -> 1 | J7: =IF(H7="Break","",IFERROR(I7/(SUM($I$6:$I$12)-$I$12),0)) -> 0.125
A8: 09:00 | B8: Focus | H8: Customer | I8: =COUNTIF($B$6:$F$23,H8)*0.5 -> 1.5 | J8: =IF(H8="Break","",IFERROR(I8/(SUM($I$6:$I$12)-$I$12),0)) -> 0.1875
A9: 09:30 | B9: Customer | H9: People/Coaching | I9: =COUNTIF($B$6:$F$23,H9)*0.5 -> 0.5 | J9: =IF(H9="Break","",IFERROR(I9/(SUM($I$6:$I$12)-$I$12),0)) -> 0.0625
A10: 10:00 | B10: Customer | H10: Admin/Batch | I10: =COUNTIF($B$6:$F$23,H10)*0.5 -> 1.5 | J10: =IF(H10="Break","",IFERROR(I10/(SUM($I$6:$I$12)-$I$12),0)) -> 0.1875
A11: 10:30 | B11: Buffer | H11: Buffer | I11: =COUNTIF($B$6:$F$23,H11)*0.5 -> 1.5 | J11: =IF(H11="Break","",IFERROR(I11/(SUM($I$6:$I$12)-$I$12),0)) -> 0.1875
A12: 11:00 | B12: Admin/Batch | H12: Break | I12: =COUNTIF($B$6:$F$23,H12)*0.5 -> 1 | J12: =IF(H12="Break","",IFERROR(I12/(SUM($I$6:$I$12)-$I$12),0))
A13: 11:30 | B13: Meeting
A14: 12:00 | B14: Break | H14: Status buffer | I14: =IF(J11="","",IF(AND(J11>=0.15,J11<=0.2),"IDEAL",IF(J11<0.15,"Kurang buffer","Buffer berlebih"))) -> IDEAL
A15: 12:30 | B15: Break | H15: Status focus | I15: =IF(J6>=0.2,"Focus cukup","Tambah focus block") -> Focus cukup
A16: 13:00 | B16: People/Coaching
A17: 13:30 | B17: Focus | H17: Prinsip: rencanakan 80–85%, buffer 15–20%. Focus block di jam energi puncak. Email/approval di-batch.
A18: 14:00 | B18: Focus
A19: 14:30 | B19: Buffer
A20: 15:00 | B20: Customer
A21: 15:30 | B21: Admin/Batch
A22: 16:00 | B22: Meeting
A23: 16:30 | B23: Buffer

Sheet 5 Big3 & Meeting
A1: Daily Big 3 & Meeting Checklist
A2: Tulis 3 hasil (outcome) setiap pagi sebelum membuka email. Tandai Y bila selesai.
A3: Legenda: sel kuning = diisi peserta/trainer (teks biru); sel putih/abu = otomatis (rumus) atau panduan.
A5: Tanggal | B5: Big 1 (dampak tertinggi) | C5: Done? | D5: Big 2 (risk/compliance) | E5: Done? | F5: Big 3 (people/improvement) | G5: Done? | H5: Skor hari
B6: Keputusan kredit nasabah X tuntas | C6: Y | D6: 2 audit finding ditutup dengan evidence | E6: N | F6: Coaching 30 menit dengan officer baru | G6: Y | H6: =IF(B6="","",COUNTIF(C6,"Y")+COUNTIF(E6,"Y")+COUNTIF(G6,"Y")&"/3") -> 2/3
H7: =IF(B7="","",COUNTIF(C7,"Y")+COUNTIF(E7,"Y")+COUNTIF(G7,"Y")&"/3")
H8: =IF(B8="","",COUNTIF(C8,"Y")+COUNTIF(E8,"Y")+COUNTIF(G8,"Y")&"/3")
H9: =IF(B9="","",COUNTIF(C9,"Y")+COUNTIF(E9,"Y")+COUNTIF(G9,"Y")&"/3")
H10: =IF(B10="","",COUNTIF(C10,"Y")+COUNTIF(E10,"Y")+COUNTIF(G10,"Y")&"/3")
H11: =IF(B11="","",COUNTIF(C11,"Y")+COUNTIF(E11,"Y")+COUNTIF(G11,"Y")&"/3")
H12: =IF(B12="","",COUNTIF(C12,"Y")+COUNTIF(E12,"Y")+COUNTIF(G12,"Y")&"/3")
H13: =IF(B13="","",COUNTIF(C13,"Y")+COUNTIF(E13,"Y")+COUNTIF(G13,"Y")&"/3")
H14: =IF(B14="","",COUNTIF(C14,"Y")+COUNTIF(E14,"Y")+COUNTIF(G14,"Y")&"/3")
H15: =IF(B15="","",COUNTIF(C15,"Y")+COUNTIF(E15,"Y")+COUNTIF(G15,"Y")&"/3")
A16: Tingkat penyelesaian | B16: =IFERROR((COUNTIF(C6:C15,"Y")+COUNTIF(E6:E15,"Y")+COUNTIF(G6:G15,"Y"))/(3*COUNTA(B6:B15)),"") -> 0.66666667
A18: Meeting Checklist (Go / No-Go)
A19: No | B19: Pertanyaan | C19: Y/N | D19: Wajib?
A20: 1 | B20: Tujuan meeting jelas dan tertulis | D20: Ya
A21: 2 | B21: Agenda dikirim sebelum meeting | D21: Tidak
A22: 3 | B22: Keputusan yang dibutuhkan sudah jelas | D22: Ya
A23: 4 | B23: Hanya peserta yang relevan diundang | D23: Tidak
A24: 5 | B24: Durasi ≤ 45 menit | D24: Tidak
A25: 6 | B25: Ada notulen aksi (owner, deadline) | D25: Tidak
A26: 7 | B26: Tidak bisa diganti update tertulis | D26: Ya
B27: Keputusan | C27: =IF(COUNTA(C20:C26)<7,"Lengkapi",IF(AND(C20="Y",C22="Y",C26="Y"),IF(COUNTIF(C20:C26,"Y")>=5,"GO","GO dengan perbaikan"),"NO-GO / ganti update tertulis")) -> Lengkapi

Sheet 6 Delegation
A1: Delegation Contract, Level Guide & RACI
A2: Isi satu kolom per delegasi. Sistem memeriksa kelengkapan 8 elemen.
A3: Legenda: sel kuning = diisi peserta/trainer (teks biru); sel putih/abu = otomatis (rumus) atau panduan.
A5: Elemen | B5: Delegasi 1 | C5: Delegasi 2 | D5: Delegasi 3
A6: Didelegasikan kepada | B6: Rina (Ops Supervisor)
A7: Level (L1–L5) | B7: L3
A8: WHAT – tugas apa | B8: Menyusun rencana penutupan 3 temuan audit KYC
A9: WHY – mengapa penting | B9: Tenggat komitmen ke audit internal 2 minggu lagi
A10: EXPECTED OUTCOME | B10: Rencana tindakan + dokumen pendukung siap divalidasi
A11: AUTHORITY – boleh memutuskan apa | B11: Menentukan urutan perbaikan dan PIC per berkas
A12: BOUNDARY – batas biaya/risiko/kebijakan | B12: Tidak mengubah kebijakan; biaya Rp0
A13: DEADLINE | B13: [tgl]
A14: CHECKPOINT | B14: Setiap Selasa 15.00
A15: EVIDENCE – bukti selesai | B15: Upload evidence ke sistem audit
A16: Kelengkapan (8 elemen) | B16: =IF(B6="","",COUNTA(B8:B15)&"/8"&IF(COUNTA(B8:B15)<8," — lengkapi","")) -> 8/8 | C16: =IF(C6="","",COUNTA(C8:C15)&"/8"&IF(COUNTA(C8:C15)<8," — lengkapi","")) | D16: =IF(D6="","",COUNTA(D8:D15)&"/8"&IF(COUNTA(D8:D15)<8," — lengkapi",""))
A18: Delegation Level Guide
A19: Level | B19: Nama | C19: Arti | D19: Cocok untuk
A20: L1 | B20: Research | C20: Kumpulkan fakta, saya memutuskan | D20: Staf baru, isu sensitif
A21: L2 | B21: Analyze | C21: Analisis dan sajikan opsi | D21: Staf berkembang
A22: L3 | B22: Recommend | C22: Rekomendasikan satu opsi | D22: Staf kompeten
A23: L4 | B23: Decide & inform | C23: Putuskan, lalu informasikan | D23: Staf senior terpercaya
A24: L5 | B24: Own | C24: Pemilik penuh | D24: Calon leader / talent pool
A26: RACI Matrix (isi R / A / C / I)
A27: Aktivitas | B27: Branch Mgr | C27: Ops Supervisor | D27: Officer | E27: Internal Audit | F27: Cek: jumlah A
A28: Analisis akar masalah | B28: C | C28: A | D28: R | E28: C | F28: =IF(A28="","",IF(COUNTIF(B28:E28,"*A*")=1,"OK (1 A)","Harus tepat 1 A")) -> OK (1 A)
F29: =IF(A29="","",IF(COUNTIF(B29:E29,"*A*")=1,"OK (1 A)","Harus tepat 1 A"))
F30: =IF(A30="","",IF(COUNTIF(B30:E30,"*A*")=1,"OK (1 A)","Harus tepat 1 A"))
F31: =IF(A31="","",IF(COUNTIF(B31:E31,"*A*")=1,"OK (1 A)","Harus tepat 1 A"))
F32: =IF(A32="","",IF(COUNTIF(B32:E32,"*A*")=1,"OK (1 A)","Harus tepat 1 A"))
F33: =IF(A33="","",IF(COUNTIF(B33:E33,"*A*")=1,"OK (1 A)","Harus tepat 1 A"))
F34: =IF(A34="","",IF(COUNTIF(B34:E34,"*A*")=1,"OK (1 A)","Harus tepat 1 A"))
F35: =IF(A35="","",IF(COUNTIF(B35:E35,"*A*")=1,"OK (1 A)","Harus tepat 1 A"))

Sheet 7 GROW & SBI
A1: GROW Coaching Sheet & SBI Feedback Card
A2: Leader bertanya, staf menjawab. SBI menyusun kalimat feedback otomatis.
A3: Legenda: sel kuning = diisi peserta/trainer (teks biru); sel putih/abu = otomatis (rumus) atau panduan.
A5: Tahap | B5: Pertanyaan pemandu | C5: Jawaban staf / catatan
A6: Goal | B6: Hasil seperti apa yang ingin dicapai akhir bulan? Bagaimana kita tahu tercapai?
A7: Reality | B7: Apa yang sudah dicoba? Apa hambatannya? Berapa realisasi saat ini?
A8: Options | B8: Apa saja cara lain? Jika tanpa batasan, apa yang dilakukan? Siapa yang bisa membantu?
A9: Way Forward | B9: Apa langkah pertama? Kapan? Dukungan apa yang dibutuhkan? Kapan cek lagi?
A10: Observer: jumlah pertanyaan
A11: Observer: jumlah pernyataan/solusi
A12: Rasio bertanya | B12: =IFERROR(B10/(B10+B11),"")
A14: SBI + Next Expectation Feedback Card
A15: Elemen | B15: Isi | C15: Contoh
A16: Situation | B16: Pada laporan rekonsiliasi kemarin, | C16: Pada laporan rekonsiliasi kemarin,
A17: Behavior | B17: dua angka belum direkonsiliasi, | C17: dua angka belum direkonsiliasi,
A18: Impact | B18: akibatnya review harus diulang. | C18: akibatnya review harus diulang
A19: Next Expectation | B19: Untuk laporan berikutnya, lakukan checklist sebelum submit. | C19: untuk laporan berikutnya lakukan checklist sebelum submit.
A20: Kalimat feedback | B20: =TRIM(B16&" "&B17&" "&B18&" "&B19) -> Pada laporan rekonsiliasi kemarin, dua angka belum direkonsiliasi, akibatnya review harus diulang. Untuk laporan berikutnya, lakukan checklist sebelum submit.
A21: Cek kualitas | B21: =IF(COUNTA(B16:B19)<4,"Lengkapi 4 elemen","Lengkap — pastikan B adalah perilaku teramati, bukan sifat") -> Lengkap — pastikan B adalah perilaku teramati, bukan sifat

Sheet 8 Fact-Assumption
A1: Fact-Assumption-Opinion Sheet & Critical Thinking Questions
A2: Klasifikasikan setiap pernyataan sebelum menyimpulkan.
A3: Legenda: sel kuning = diisi peserta/trainer (teks biru); sel putih/abu = otomatis (rumus) atau panduan.
A5: Pernyataan | B5: Jenis | C5: Evidence yang ada | D5: How do we know? (sumber) | E5: Better question
A6: NPL naik karena ekonomi | B6: Assumption | C6: NPL naik 0,4% (data) | D6: Laporan kualitas aset bulanan | E6: Segmen, produk, vintage mana yang memburuk?
A16: Jumlah asumsi/opini yang belum diverifikasi | B16: =COUNTIF(B6:B15,"Assumption")+COUNTIF(B6:B15,"Opinion")+COUNTIF(B6:B15,"Unknown") -> 1
A18: Critical Thinking Questions Card
A19: What? | B19: Apa yang sebenarnya terjadi?
A20: How do we know? | B20: Apa buktinya, dari sumber mana?
A21: Why? | B21: Mengapa terjadi?
A22: What else? | B22: Penjelasan lain apa yang mungkin?
A23: So what? | B23: Apa dampaknya?
A24: What if? | B24: Bagaimana jika kita salah?
A25: Now what? | B25: Apa tindakan selanjutnya?

Sheet 9 Root Cause
A1: 5 Whys, Fishbone & Issue Tree
A2: Gunakan fishbone untuk memetakan penyebab, 5 Whys untuk menggali kandidat terkuat, issue tree untuk memecah masalah.
A3: Legenda: sel kuning = diisi peserta/trainer (teks biru); sel putih/abu = otomatis (rumus) atau panduan.
A5: Problem statement | B5: Customer complaint naik 40% dalam 3 bulan
A7: 5 Whys | B7: Jawaban | C7: Evidence? (Y/N) | D7: Sumber evidence
A8: Why 1
A9: Why 2
A10: Why 3
A11: Why 4
A12: Why 5
A13: Root cause kandidat | B13: =IFERROR(LOOKUP(2,1/(B8:B12<>""),B8:B12),"")
A14: Cek | B14: =IF(B13="","",IF(COUNTIF(C8:C12,"N")>0,"Ada jawaban tanpa evidence — verifikasi dulu","Didukung evidence"))
A16: Kategori Fishbone | B16: Penyebab potensial | C16: Evidence? (Y/N) | D16: Data pendukung | E16: Kandidat root cause?
A17: People | E17: =IF(AND(B17<>"",C17="Y"),"Ya — gali dengan 5 Whys","")
E18: =IF(AND(B18<>"",C18="Y"),"Ya — gali dengan 5 Whys","")
A19: Process | E19: =IF(AND(B19<>"",C19="Y"),"Ya — gali dengan 5 Whys","")
E20: =IF(AND(B20<>"",C20="Y"),"Ya — gali dengan 5 Whys","")
A21: Technology | E21: =IF(AND(B21<>"",C21="Y"),"Ya — gali dengan 5 Whys","")
E22: =IF(AND(B22<>"",C22="Y"),"Ya — gali dengan 5 Whys","")
A23: Policy | E23: =IF(AND(B23<>"",C23="Y"),"Ya — gali dengan 5 Whys","")
E24: =IF(AND(B24<>"",C24="Y"),"Ya — gali dengan 5 Whys","")
A25: Data | E25: =IF(AND(B25<>"",C25="Y"),"Ya — gali dengan 5 Whys","")
E26: =IF(AND(B26<>"",C26="Y"),"Ya — gali dengan 5 Whys","")
A27: External | E27: =IF(AND(B27<>"",C27="Y"),"Ya — gali dengan 5 Whys","")
E28: =IF(AND(B28<>"",C28="Y"),"Ya — gali dengan 5 Whys","")
A31: Level 0 (masalah) | B31: Level 1 (MECE) | C31: Level 2 (driver) | D31: Metric / data | E31: Evidence status
A32: Branch profit decline | B32: Revenue | C32: Volume kredit & dana | D32: Outstanding vs target
C33: Spread / NIM | D33: NIM bulanan
C34: Fee-based income | D34: Fee per produk
B35: Cost | C35: Biaya dana | D35: Cost of fund
C36: Biaya operasional | D36: Opex per bulan
B37: Credit Loss | C37: NPL baru per segmen | D37: NPL per vintage
C38: Pencadangan | D38: CKPN

Sheet 10 Bias Checklist
A1: Bias Checklist sebelum memutuskan
A2: Jawab Y bila tanda bias terdeteksi; tuliskan mitigasi.
A3: Legenda: sel kuning = diisi peserta/trainer (teks biru); sel putih/abu = otomatis (rumus) atau panduan.
A5: Bias | B5: Pertanyaan pengecekan | C5: Terdeteksi? (Y/N) | D5: Mitigasi / better question
A6: Confirmation | B6: Apakah kita hanya mencari data yang mendukung pilihan awal?
A7: Anchoring | B7: Apakah kita terpaku pada angka/usulan pertama?
A8: Authority | B8: Apakah kita memilih karena pejabat tertinggi menyukainya?
A9: Availability | B9: Apakah kita menilai dari kejadian yang paling mudah diingat?
A10: Halo Effect | B10: Apakah satu kesan baik menutupi risiko lain?
A11: Recency | B11: Apakah kejadian terbaru terlalu mendominasi penilaian?
A12: Status Quo | B12: Apakah kita menolak opsi baru hanya karena berbeda?
A13: Sunk Cost | B13: Apakah kita melanjutkan karena biaya yang sudah keluar?
A14: Overconfidence | B14: Apakah kita terlalu yakin tanpa skenario gagal?
A15: Groupthink | B15: Apakah ada yang ragu tetapi diam demi harmoni?
A16: Jumlah bias terdeteksi | C16: =COUNTIF(C6:C15,"Y") -> 0
A17: Rekomendasi | B17: =IF(C16>=3,"Tunda keputusan: tunjuk devil's advocate & cari evidence tambahan",IF(C16>=1,"Lanjut dengan mitigasi tertulis","Lanjut")) -> Lanjut

Sheet 11 Decision Matrix
A1: Decision Matrix (9 kriteria)
A2: Skor 1–5 (5 = paling menguntungkan). Untuk Risk & Execution Difficulty: risiko rendah / mudah = skor tinggi.
A3: Legenda: sel kuning = diisi peserta/trainer (teks biru); sel putih/abu = otomatis (rumus) atau panduan.
A5: Kriteria | B5: Bobot | C5: Opsi A | D5: Opsi B | E5: Opsi C | F5: Opsi D
A6: Nama opsi → | C6: Process redesign | D6: Hire staff | E6: Automation
A7: Business Impact | B7: 0.15 | C7: 4 | D7: 3 | E7: 5
A8: Customer Impact | B8: 0.15 | C8: 4 | D8: 3 | E8: 4
A9: Risk | B9: 0.15 | C9: 4 | D9: 4 | E9: 2
A10: Compliance | B10: 0.15 | C10: 4 | D10: 4 | E10: 3
A11: Financial Impact | B11: 0.1 | C11: 3 | D11: 2 | E11: 4
A12: Execution Difficulty | B12: 0.1 | C12: 3 | D12: 4 | E12: 2
A13: Resources | B13: 0.05 | C13: 4 | D13: 2 | E13: 2
A14: Urgency | B14: 0.1 | C14: 4 | D14: 3 | E14: 2
A15: Reversibility | B15: 0.05 | C15: 4 | D15: 3 | E15: 1
A16: Total bobot (harus 100%) | B16: =SUM(B7:B15) -> 1
A17: SKOR TERTIMBANG | C17: =IF(OR(C6="",COUNT(C7:C15)<9),"",SUMPRODUCT(C7:C15,$B$7:$B$15)/$B$16) -> 3.8 | D17: =IF(OR(D6="",COUNT(D7:D15)<9),"",SUMPRODUCT(D7:D15,$B$7:$B$15)/$B$16) -> 3.25 | E17: =IF(OR(E6="",COUNT(E7:E15)<9),"",SUMPRODUCT(E7:E15,$B$7:$B$15)/$B$16) -> 3.05 | F17: =IF(OR(F6="",COUNT(F7:F15)<9),"",SUMPRODUCT(F7:F15,$B$7:$B$15)/$B$16)
A18: Peringkat | C18: =IF(C17="","",RANK(C17,$C$17:$F$17)) -> 1 | D18: =IF(D17="","",RANK(D17,$C$17:$F$17)) -> 2 | E18: =IF(E17="","",RANK(E17,$C$17:$F$17)) -> 3 | F18: =IF(F17="","",RANK(F17,$C$17:$F$17))
A19: Reversibility check | C19: =IF(C15="","",IF(C15<=2,"Hard-to-reverse: pre-mortem","Reversible")) -> Reversible | D19: =IF(D15="","",IF(D15<=2,"Hard-to-reverse: pre-mortem","Reversible")) -> Reversible | E19: =IF(E15="","",IF(E15<=2,"Hard-to-reverse: pre-mortem","Reversible")) -> Hard-to-reverse: pre-mortem | F19: =IF(F15="","",IF(F15<=2,"Hard-to-reverse: pre-mortem","Reversible"))
A21: Opsi skor tertinggi | B21: =IFERROR(INDEX(C6:F6,MATCH(MAX(C17:F17),C17:F17,0)),"") -> Process redesign
A22: Catatan: matriks adalah alat diskusi. Jika hasil terasa salah, cari kriteria yang belum tertangkap.

Sheet 12 Pre-Mortem
A1: Pre-Mortem: Failure → Warning → Prevention
A2: Bayangkan 6 bulan lagi keputusan ini gagal total. Tulis alasannya, tanda awalnya, dan pencegahannya.
A3: Legenda: sel kuning = diisi peserta/trainer (teks biru); sel putih/abu = otomatis (rumus) atau panduan.
A5: Keputusan yang diuji
A6: Failure (apa yang salah) | B6: Why | C6: Warning sign | D6: Prevention (tindakan sekarang) | E6: Owner | F6: Due | G6: Likelihood 1–5 | H6: Impact 1–5 | I6: Risk score | J6: Prioritas
A7: Otomasi tidak dipakai staf | B7: Pelatihan minim | C7: Login sistem rendah di bulan 1 | D7: Super-user per cabang + target adopsi mingguan | E7: Ops Head | G7: 4 | H7: 4 | I7: =IF(OR(G7="",H7=""),"",G7*H7) -> 16 | J7: =IF(I7="","",IF(I7>=15,"High",IF(I7>=8,"Medium","Low"))) -> High
I8: =IF(OR(G8="",H8=""),"",G8*H8) | J8: =IF(I8="","",IF(I8>=15,"High",IF(I8>=8,"Medium","Low")))
I9: =IF(OR(G9="",H9=""),"",G9*H9) | J9: =IF(I9="","",IF(I9>=15,"High",IF(I9>=8,"Medium","Low")))
I10: =IF(OR(G10="",H10=""),"",G10*H10) | J10: =IF(I10="","",IF(I10>=15,"High",IF(I10>=8,"Medium","Low")))
I11: =IF(OR(G11="",H11=""),"",G11*H11) | J11: =IF(I11="","",IF(I11>=15,"High",IF(I11>=8,"Medium","Low")))
I12: =IF(OR(G12="",H12=""),"",G12*H12) | J12: =IF(I12="","",IF(I12>=15,"High",IF(I12>=8,"Medium","Low")))
I13: =IF(OR(G13="",H13=""),"",G13*H13) | J13: =IF(I13="","",IF(I13>=15,"High",IF(I13>=8,"Medium","Low")))
I14: =IF(OR(G14="",H14=""),"",G14*H14) | J14: =IF(I14="","",IF(I14>=15,"High",IF(I14>=8,"Medium","Low")))

Sheet 13 Decision Log
A1: Decision Log
A2: Catat setiap keputusan penting untuk dipelajari kembali (Learning Leadership).
A3: Legenda: sel kuning = diisi peserta/trainer (teks biru); sel putih/abu = otomatis (rumus) atau panduan.
A5: Tanggal | B5: Keputusan | C5: Opsi yang dipertimbangkan | D5: Evidence utama | E5: Diputuskan oleh | F5: Reversible? | G5: Review date | H5: Outcome | I5: Lesson learned

Sheet 14 Action Tracker
A1: Action Tracker
A2: No owner = no action. No deadline = no commitment. No evidence = no closure.
A3: Legenda: sel kuning = diisi peserta/trainer (teks biru); sel putih/abu = otomatis (rumus) atau panduan.
A5: No | B5: Action | C5: Owner | D5: Deadline | E5: Evidence | F5: Checkpoint | G5: Status | H5: Valid? | I5: Overdue?
A6: 1 | B6: Pre-check dokumen kredit di RM | C6: Ops Head | E6: Checklist terisi 100% berkas | F6: Mingguan | G6: On track | H6: =IF(B6="","",IF(AND(C6<>"",D6<>"",E6<>""),"Valid","Tidak valid")) -> Tidak valid | I6: =IF(OR(B6="",D6=""),"",IF(AND(G6<>"Done",D6<TODAY()),"OVERDUE",""))
A7: 2 | H7: =IF(B7="","",IF(AND(C7<>"",D7<>"",E7<>""),"Valid","Tidak valid")) | I7: =IF(OR(B7="",D7=""),"",IF(AND(G7<>"Done",D7<TODAY()),"OVERDUE",""))
A8: 3 | H8: =IF(B8="","",IF(AND(C8<>"",D8<>"",E8<>""),"Valid","Tidak valid")) | I8: =IF(OR(B8="",D8=""),"",IF(AND(G8<>"Done",D8<TODAY()),"OVERDUE",""))
A9: 4 | H9: =IF(B9="","",IF(AND(C9<>"",D9<>"",E9<>""),"Valid","Tidak valid")) | I9: =IF(OR(B9="",D9=""),"",IF(AND(G9<>"Done",D9<TODAY()),"OVERDUE",""))
A10: 5 | H10: =IF(B10="","",IF(AND(C10<>"",D10<>"",E10<>""),"Valid","Tidak valid")) | I10: =IF(OR(B10="",D10=""),"",IF(AND(G10<>"Done",D10<TODAY()),"OVERDUE",""))
A11: 6 | H11: =IF(B11="","",IF(AND(C11<>"",D11<>"",E11<>""),"Valid","Tidak valid")) | I11: =IF(OR(B11="",D11=""),"",IF(AND(G11<>"Done",D11<TODAY()),"OVERDUE",""))
A12: 7 | H12: =IF(B12="","",IF(AND(C12<>"",D12<>"",E12<>""),"Valid","Tidak valid")) | I12: =IF(OR(B12="",D12=""),"",IF(AND(G12<>"Done",D12<TODAY()),"OVERDUE",""))
A13: 8 | H13: =IF(B13="","",IF(AND(C13<>"",D13<>"",E13<>""),"Valid","Tidak valid")) | I13: =IF(OR(B13="",D13=""),"",IF(AND(G13<>"Done",D13<TODAY()),"OVERDUE",""))
A14: 9 | H14: =IF(B14="","",IF(AND(C14<>"",D14<>"",E14<>""),"Valid","Tidak valid")) | I14: =IF(OR(B14="",D14=""),"",IF(AND(G14<>"Done",D14<TODAY()),"OVERDUE",""))
A15: 10 | H15: =IF(B15="","",IF(AND(C15<>"",D15<>"",E15<>""),"Valid","Tidak valid")) | I15: =IF(OR(B15="",D15=""),"",IF(AND(G15<>"Done",D15<TODAY()),"OVERDUE",""))
A16: 11 | H16: =IF(B16="","",IF(AND(C16<>"",D16<>"",E16<>""),"Valid","Tidak valid")) | I16: =IF(OR(B16="",D16=""),"",IF(AND(G16<>"Done",D16<TODAY()),"OVERDUE",""))
A17: 12 | H17: =IF(B17="","",IF(AND(C17<>"",D17<>"",E17<>""),"Valid","Tidak valid")) | I17: =IF(OR(B17="",D17=""),"",IF(AND(G17<>"Done",D17<TODAY()),"OVERDUE",""))
A18: 13 | H18: =IF(B18="","",IF(AND(C18<>"",D18<>"",E18<>""),"Valid","Tidak valid")) | I18: =IF(OR(B18="",D18=""),"",IF(AND(G18<>"Done",D18<TODAY()),"OVERDUE",""))
... A25: 20 | H25: =IF(B25="","",IF(AND(C25<>"",D25<>"",E25<>""),"Valid","Tidak valid")) | I25: =IF(OR(B25="",D25=""),"",IF(AND(G25<>"Done",D25<TODAY()),"OVERDUE",""))
A27: Total action | B27: =COUNTA(B6:B25) -> 1
A28: Done | B28: =COUNTIF(G6:G25,"Done") -> 0
A29: Action closure rate | B29: =IFERROR(B28/B27,0) -> 0
A30: Overdue | B30: =COUNTIF(I6:I25,"OVERDUE") -> 0
A31: Tidak valid | B31: =COUNTIF(H6:H25,"Tidak valid") -> 1

Sheet 15 Arena Scoring
A1: Banking Leadership Arena · Scoring (4 tim)
A2: Isi pilihan tiap tim: Do / Delegate / Escalate / Defer. Poin, waktu, penalti dihitung otomatis. Parameter kolom B–E bisa diubah trainer.
A3: Legenda: sel kuning = diisi peserta/trainer (teks biru); sel putih/abu = otomatis (rumus) atau panduan.
A5: Waktu Delegate / Escalate / Defer (menit) → | B5: 15 | C5: 10 | D5: 0
A6: Kejadian | B6: Dimensi | C6: Best | D6: Acceptable | E6: Menit Do | F6: Tim 1 pilihan | G6: Poin | H6: Menit | I6: Penalti | J6: Tim 2 pilihan | K6: Poin | L6: Menit | M6: Penalti | N6: Tim 3 pilihan | O6: Poin | P6: Menit | Q6: Penalti | R6: Tim 4 pilihan | S6: Poin | T6: Menit | U6: Penalti
A7: Nasabah prioritas komplain di hall | B7: Customer | C7: Do | D7: Delegate | E7: 30 | F7: Do | G7: =IF(F7="","",IF(F7=C7,10,IF(F7=D7,5,0))) -> 10 | H7: =IF(F7="","",IF(F7="Do",E7,IF(F7="Delegate",$B$5,IF(F7="Escalate",$C$5,$D$5)))) -> 30 | I7: =IF(AND(B7="Risk",F7="Defer"),-10,0) -> 0 | J7: Do | K7: =IF(J7="","",IF(J7=C7,10,IF(J7=D7,5,0))) -> 10 | L7: =IF(J7="","",IF(J7="Do",E7,IF(J7="Delegate",$B$5,IF(J7="Escalate",$C$5,$D$5)))) -> 30 | M7: =IF(AND(B7="Risk",J7="Defer"),-10,0) -> 0 | O7: =IF(N7="","",IF(N7=C7,10,IF(N7=D7,5,0))) | P7: =IF(N7="","",IF(N7="Do",E7,IF(N7="Delegate",$B$5,IF(N7="Escalate",$C$5,$D$5)))) | Q7: =IF(AND(B7="Risk",N7="Defer"),-10,0) -> 0 | S7: =IF(R7="","",IF(R7=C7,10,IF(R7=D7,5,0))) | T7: =IF(R7="","",IF(R7="Do",E7,IF(R7="Delegate",$B$5,IF(R7="Escalate",$C$5,$D$5)))) | U7: =IF(AND(B7="Risk",R7="Defer"),-10,0) -> 0
A8: Fraud alert transaksi tidak wajar | B8: Risk | C8: Escalate | D8: Do | E8: 45 | F8: Escalate | G8: =IF(F8="","",IF(F8=C8,10,IF(F8=D8,5,0))) -> 10 | H8: =IF(F8="","",IF(F8="Do",E8,IF(F8="Delegate",$B$5,IF(F8="Escalate",$C$5,$D$5)))) -> 10 | I8: =IF(AND(B8="Risk",F8="Defer"),-10,0) -> 0 | J8: Defer | K8: =IF(J8="","",IF(J8=C8,10,IF(J8=D8,5,0))) -> 0 | L8: =IF(J8="","",IF(J8="Do",E8,IF(J8="Delegate",$B$5,IF(J8="Escalate",$C$5,$D$5)))) -> 0 | M8: =IF(AND(B8="Risk",J8="Defer"),-10,0) -> -10 | O8: =IF(N8="","",IF(N8=C8,10,IF(N8=D8,5,0))) | P8: =IF(N8="","",IF(N8="Do",E8,IF(N8="Delegate",$B$5,IF(N8="Escalate",$C$5,$D$5)))) | Q8: =IF(AND(B8="Risk",N8="Defer"),-10,0) -> 0 | S8: =IF(R8="","",IF(R8=C8,10,IF(R8=D8,5,0))) | T8: =IF(R8="","",IF(R8="Do",E8,IF(R8="Delegate",$B$5,IF(R8="Escalate",$C$5,$D$5)))) | U8: =IF(AND(B8="Risk",R8="Defer"),-10,0) -> 0
A9: Review target funding mingguan | B9: Business | C9: Do | D9: Delegate | E9: 45 | F9: Do | G9: =IF(F9="","",IF(F9=C9,10,IF(F9=D9,5,0))) -> 10 | H9: =IF(F9="","",IF(F9="Do",E9,IF(F9="Delegate",$B$5,IF(F9="Escalate",$C$5,$D$5)))) -> 45 | I9: =IF(AND(B9="Risk",F9="Defer"),-10,0) -> 0 | J9: Do | K9: =IF(J9="","",IF(J9=C9,10,IF(J9=D9,5,0))) -> 10 | L9: =IF(J9="","",IF(J9="Do",E9,IF(J9="Delegate",$B$5,IF(J9="Escalate",$C$5,$D$5)))) -> 45 | M9: =IF(AND(B9="Risk",J9="Defer"),-10,0) -> 0 | O9: =IF(N9="","",IF(N9=C9,10,IF(N9=D9,5,0))) | P9: =IF(N9="","",IF(N9="Do",E9,IF(N9="Delegate",$B$5,IF(N9="Escalate",$C$5,$D$5)))) | Q9: =IF(AND(B9="Risk",N9="Defer"),-10,0) -> 0 | S9: =IF(R9="","",IF(R9=C9,10,IF(R9=D9,5,0))) | T9: =IF(R9="","",IF(R9="Do",E9,IF(R9="Delegate",$B$5,IF(R9="Escalate",$C$5,$D$5)))) | U9: =IF(AND(B9="Risk",R9="Defer"),-10,0) -> 0
A10: Officer baru minta arahan | B10: People | C10: Delegate | D10: Do | E10: 30 | F10: Delegate | G10: =IF(F10="","",IF(F10=C10,10,IF(F10=D10,5,0))) -> 10 | H10: =IF(F10="","",IF(F10="Do",E10,IF(F10="Delegate",$B$5,IF(F10="Escalate",$C$5,$D$5)))) -> 15 | I10: =IF(AND(B10="Risk",F10="Defer"),-10,0) -> 0 | J10: Do | K10: =IF(J10="","",IF(J10=C10,10,IF(J10=D10,5,0))) -> 5 | L10: =IF(J10="","",IF(J10="Do",E10,IF(J10="Delegate",$B$5,IF(J10="Escalate",$C$5,$D$5)))) -> 30 | M10: =IF(AND(B10="Risk",J10="Defer"),-10,0) -> 0 | O10: =IF(N10="","",IF(N10=C10,10,IF(N10=D10,5,0))) | P10: =IF(N10="","",IF(N10="Do",E10,IF(N10="Delegate",$B$5,IF(N10="Escalate",$C$5,$D$5)))) | Q10: =IF(AND(B10="Risk",N10="Defer"),-10,0) -> 0 | S10: =IF(R10="","",IF(R10=C10,10,IF(R10=D10,5,0))) | T10: =IF(R10="","",IF(R10="Do",E10,IF(R10="Delegate",$B$5,IF(R10="Escalate",$C$5,$D$5)))) | U10: =IF(AND(B10="Risk",R10="Defer"),-10,0) -> 0
A11: Laporan regulator jatuh tempo hari ini | B11: Risk | C11: Do | D11: Delegate | E11: 60 | F11: Do | G11: =IF(F11="","",IF(F11=C11,10,IF(F11=D11,5,0))) -> 10 | H11: =IF(F11="","",IF(F11="Do",E11,IF(F11="Delegate",$B$5,IF(F11="Escalate",$C$5,$D$5)))) -> 60 | I11: =IF(AND(B11="Risk",F11="Defer"),-10,0) -> 0 | J11: Delegate | K11: =IF(J11="","",IF(J11=C11,10,IF(J11=D11,5,0))) -> 5 | L11: =IF(J11="","",IF(J11="Do",E11,IF(J11="Delegate",$B$5,IF(J11="Escalate",$C$5,$D$5)))) -> 15 | M11: =IF(AND(B11="Risk",J11="Defer"),-10,0) -> 0 | O11: =IF(N11="","",IF(N11=C11,10,IF(N11=D11,5,0))) | P11: =IF(N11="","",IF(N11="Do",E11,IF(N11="Delegate",$B$5,IF(N11="Escalate",$C$5,$D$5)))) | Q11: =IF(AND(B11="Risk",N11="Defer"),-10,0) -> 0 | S11: =IF(R11="","",IF(R11=C11,10,IF(R11=D11,5,0))) | T11: =IF(R11="","",IF(R11="Do",E11,IF(R11="Delegate",$B$5,IF(R11="Escalate",$C$5,$D$5)))) | U11: =IF(AND(B11="Risk",R11="Defer"),-10,0) -> 0
A12: Kantor wilayah minta data 1 jam | B12: Execution | C12: Delegate | D12: Do | E12: 40 | G12: =IF(F12="","",IF(F12=C12,10,IF(F12=D12,5,0))) | H12: =IF(F12="","",IF(F12="Do",E12,IF(F12="Delegate",$B$5,IF(F12="Escalate",$C$5,$D$5)))) | I12: =IF(AND(B12="Risk",F12="Defer"),-10,0) -> 0 | K12: =IF(J12="","",IF(J12=C12,10,IF(J12=D12,5,0))) | L12: =IF(J12="","",IF(J12="Do",E12,IF(J12="Delegate",$B$5,IF(J12="Escalate",$C$5,$D$5)))) | M12: =IF(AND(B12="Risk",J12="Defer"),-10,0) -> 0 | O12: =IF(N12="","",IF(N12=C12,10,IF(N12=D12,5,0))) | P12: =IF(N12="","",IF(N12="Do",E12,IF(N12="Delegate",$B$5,IF(N12="Escalate",$C$5,$D$5)))) | Q12: =IF(AND(B12="Risk",N12="Defer"),-10,0) -> 0 | S12: =IF(R12="","",IF(R12=C12,10,IF(R12=D12,5,0))) | T12: =IF(R12="","",IF(R12="Do",E12,IF(R12="Delegate",$B$5,IF(R12="Escalate",$C$5,$D$5)))) | U12: =IF(AND(B12="Risk",R12="Defer"),-10,0) -> 0
A13: Teller selisih kas | B13: Risk | C13: Do | D13: Escalate | E13: 30 | G13: =IF(F13="","",IF(F13=C13,10,IF(F13=D13,5,0))) | H13: =IF(F13="","",IF(F13="Do",E13,IF(F13="Delegate",$B$5,IF(F13="Escalate",$C$5,$D$5)))) | I13: =IF(AND(B13="Risk",F13="Defer"),-10,0) -> 0 | K13: =IF(J13="","",IF(J13=C13,10,IF(J13=D13,5,0))) | L13: =IF(J13="","",IF(J13="Do",E13,IF(J13="Delegate",$B$5,IF(J13="Escalate",$C$5,$D$5)))) | M13: =IF(AND(B13="Risk",J13="Defer"),-10,0) -> 0 | O13: =IF(N13="","",IF(N13=C13,10,IF(N13=D13,5,0))) | P13: =IF(N13="","",IF(N13="Do",E13,IF(N13="Delegate",$B$5,IF(N13="Escalate",$C$5,$D$5)))) | Q13: =IF(AND(B13="Risk",N13="Defer"),-10,0) -> 0 | S13: =IF(R13="","",IF(R13=C13,10,IF(R13=D13,5,0))) | T13: =IF(R13="","",IF(R13="Do",E13,IF(R13="Delegate",$B$5,IF(R13="Escalate",$C$5,$D$5)))) | U13: =IF(AND(B13="Risk",R13="Defer"),-10,0) -> 0
A14: Prospek kredit besar minta bertemu | B14: Business | C14: Do | D14: Delegate | E14: 60 | G14: =IF(F14="","",IF(F14=C14,10,IF(F14=D14,5,0))) | H14: =IF(F14="","",IF(F14="Do",E14,IF(F14="Delegate",$B$5,IF(F14="Escalate",$C$5,$D$5)))) | I14: =IF(AND(B14="Risk",F14="Defer"),-10,0) -> 0 | K14: =IF(J14="","",IF(J14=C14,10,IF(J14=D14,5,0))) | L14: =IF(J14="","",IF(J14="Do",E14,IF(J14="Delegate",$B$5,IF(J14="Escalate",$C$5,$D$5)))) | M14: =IF(AND(B14="Risk",J14="Defer"),-10,0) -> 0 | O14: =IF(N14="","",IF(N14=C14,10,IF(N14=D14,5,0))) | P14: =IF(N14="","",IF(N14="Do",E14,IF(N14="Delegate",$B$5,IF(N14="Escalate",$C$5,$D$5)))) | Q14: =IF(AND(B14="Risk",N14="Defer"),-10,0) -> 0 | S14: =IF(R14="","",IF(R14=C14,10,IF(R14=D14,5,0))) | T14: =IF(R14="","",IF(R14="Do",E14,IF(R14="Delegate",$B$5,IF(R14="Escalate",$C$5,$D$5)))) | U14: =IF(AND(B14="Risk",R14="Defer"),-10,0) -> 0
A15: ATM offline | B15: Customer | C15: Escalate | D15: Delegate | E15: 20 | G15: =IF(F15="","",IF(F15=C15,10,IF(F15=D15,5,0))) | H15: =IF(F15="","",IF(F15="Do",E15,IF(F15="Delegate",$B$5,IF(F15="Escalate",$C$5,$D$5)))) | I15: =IF(AND(B15="Risk",F15="Defer"),-10,0) -> 0 | K15: =IF(J15="","",IF(J15=C15,10,IF(J15=D15,5,0))) | L15: =IF(J15="","",IF(J15="Do",E15,IF(J15="Delegate",$B$5,IF(J15="Escalate",$C$5,$D$5)))) | M15: =IF(AND(B15="Risk",J15="Defer"),-10,0) -> 0 | O15: =IF(N15="","",IF(N15=C15,10,IF(N15=D15,5,0))) | P15: =IF(N15="","",IF(N15="Do",E15,IF(N15="Delegate",$B$5,IF(N15="Escalate",$C$5,$D$5)))) | Q15: =IF(AND(B15="Risk",N15="Defer"),-10,0) -> 0 | S15: =IF(R15="","",IF(R15=C15,10,IF(R15=D15,5,0))) | T15: =IF(R15="","",IF(R15="Do",E15,IF(R15="Delegate",$B$5,IF(R15="Escalate",$C$5,$D$5)))) | U15: =IF(AND(B15="Risk",R15="Defer"),-10,0) -> 0
A16: Dua staf konflik | B16: People | C16: Do | D16: Delegate | E16: 30 | G16: =IF(F16="","",IF(F16=C16,10,IF(F16=D16,5,0))) | H16: =IF(F16="","",IF(F16="Do",E16,IF(F16="Delegate",$B$5,IF(F16="Escalate",$C$5,$D$5)))) | I16: =IF(AND(B16="Risk",F16="Defer"),-10,0) -> 0 | K16: =IF(J16="","",IF(J16=C16,10,IF(J16=D16,5,0))) | L16: =IF(J16="","",IF(J16="Do",E16,IF(J16="Delegate",$B$5,IF(J16="Escalate",$C$5,$D$5)))) | M16: =IF(AND(B16="Risk",J16="Defer"),-10,0) -> 0 | O16: =IF(N16="","",IF(N16=C16,10,IF(N16=D16,5,0))) | P16: =IF(N16="","",IF(N16="Do",E16,IF(N16="Delegate",$B$5,IF(N16="Escalate",$C$5,$D$5)))) | Q16: =IF(AND(B16="Risk",N16="Defer"),-10,0) -> 0 | S16: =IF(R16="","",IF(R16=C16,10,IF(R16=D16,5,0))) | T16: =IF(R16="","",IF(R16="Do",E16,IF(R16="Delegate",$B$5,IF(R16="Escalate",$C$5,$D$5)))) | U16: =IF(AND(B16="Risk",R16="Defer"),-10,0) -> 0
A17: Temuan audit lewat tenggat | B17: Risk | C17: Do | D17: Delegate | E17: 45 | G17: =IF(F17="","",IF(F17=C17,10,IF(F17=D17,5,0))) | H17: =IF(F17="","",IF(F17="Do",E17,IF(F17="Delegate",$B$5,IF(F17="Escalate",$C$5,$D$5)))) | I17: =IF(AND(B17="Risk",F17="Defer"),-10,0) -> 0 | K17: =IF(J17="","",IF(J17=C17,10,IF(J17=D17,5,0))) | L17: =IF(J17="","",IF(J17="Do",E17,IF(J17="Delegate",$B$5,IF(J17="Escalate",$C$5,$D$5)))) | M17: =IF(AND(B17="Risk",J17="Defer"),-10,0) -> 0 | O17: =IF(N17="","",IF(N17=C17,10,IF(N17=D17,5,0))) | P17: =IF(N17="","",IF(N17="Do",E17,IF(N17="Delegate",$B$5,IF(N17="Escalate",$C$5,$D$5)))) | Q17: =IF(AND(B17="Risk",N17="Defer"),-10,0) -> 0 | S17: =IF(R17="","",IF(R17=C17,10,IF(R17=D17,5,0))) | T17: =IF(R17="","",IF(R17="Do",E17,IF(R17="Delegate",$B$5,IF(R17="Escalate",$C$5,$D$5)))) | U17: =IF(AND(B17="Risk",R17="Defer"),-10,0) -> 0
A18: Vendor menagih dokumen kontrak | B18: Execution | C18: Delegate | D18: Defer | E18: 20 | G18: =IF(F18="","",IF(F18=C18,10,IF(F18=D18,5,0))) | H18: =IF(F18="","",IF(F18="Do",E18,IF(F18="Delegate",$B$5,IF(F18="Escalate",$C$5,$D$5)))) | I18: =IF(AND(B18="Risk",F18="Defer"),-10,0) -> 0 | K18: =IF(J18="","",IF(J18=C18,10,IF(J18=D18,5,0))) | L18: =IF(J18="","",IF(J18="Do",E18,IF(J18="Delegate",$B$5,IF(J18="Escalate",$C$5,$D$5)))) | M18: =IF(AND(B18="Risk",J18="Defer"),-10,0) -> 0 | O18: =IF(N18="","",IF(N18=C18,10,IF(N18=D18,5,0))) | P18: =IF(N18="","",IF(N18="Do",E18,IF(N18="Delegate",$B$5,IF(N18="Escalate",$C$5,$D$5)))) | Q18: =IF(AND(B18="Risk",N18="Defer"),-10,0) -> 0 | S18: =IF(R18="","",IF(R18=C18,10,IF(R18=D18,5,0))) | T18: =IF(R18="","",IF(R18="Do",E18,IF(R18="Delegate",$B$5,IF(R18="Escalate",$C$5,$D$5)))) | U18: =IF(AND(B18="Risk",R18="Defer"),-10,0) -> 0
A19: Undangan meeting tanpa agenda | B19: Execution | C19: Defer | D19: Delegate | E19: 60 | G19: =IF(F19="","",IF(F19=C19,10,IF(F19=D19,5,0))) | H19: =IF(F19="","",IF(F19="Do",E19,IF(F19="Delegate",$B$5,IF(F19="Escalate",$C$5,$D$5)))) | I19: =IF(AND(B19="Risk",F19="Defer"),-10,0) -> 0 | K19: =IF(J19="","",IF(J19=C19,10,IF(J19=D19,5,0))) | L19: =IF(J19="","",IF(J19="Do",E19,IF(J19="Delegate",$B$5,IF(J19="Escalate",$C$5,$D$5)))) | M19: =IF(AND(B19="Risk",J19="Defer"),-10,0) -> 0 | O19: =IF(N19="","",IF(N19=C19,10,IF(N19=D19,5,0))) | P19: =IF(N19="","",IF(N19="Do",E19,IF(N19="Delegate",$B$5,IF(N19="Escalate",$C$5,$D$5)))) | Q19: =IF(AND(B19="Risk",N19="Defer"),-10,0) -> 0 | S19: =IF(R19="","",IF(R19=C19,10,IF(R19=D19,5,0))) | T19: =IF(R19="","",IF(R19="Do",E19,IF(R19="Delegate",$B$5,IF(R19="Escalate",$C$5,$D$5)))) | U19: =IF(AND(B19="Risk",R19="Defer"),-10,0) -> 0
A20: Nasabah minta restrukturisasi | B20: Business | C20: Delegate | D20: Do | E20: 45 | G20: =IF(F20="","",IF(F20=C20,10,IF(F20=D20,5,0))) | H20: =IF(F20="","",IF(F20="Do",E20,IF(F20="Delegate",$B$5,IF(F20="Escalate",$C$5,$D$5)))) | I20: =IF(AND(B20="Risk",F20="Defer"),-10,0) -> 0 | K20: =IF(J20="","",IF(J20=C20,10,IF(J20=D20,5,0))) | L20: =IF(J20="","",IF(J20="Do",E20,IF(J20="Delegate",$B$5,IF(J20="Escalate",$C$5,$D$5)))) | M20: =IF(AND(B20="Risk",J20="Defer"),-10,0) -> 0 | O20: =IF(N20="","",IF(N20=C20,10,IF(N20=D20,5,0))) | P20: =IF(N20="","",IF(N20="Do",E20,IF(N20="Delegate",$B$5,IF(N20="Escalate",$C$5,$D$5)))) | Q20: =IF(AND(B20="Risk",N20="Defer"),-10,0) -> 0 | S20: =IF(R20="","",IF(R20=C20,10,IF(R20=D20,5,0))) | T20: =IF(R20="","",IF(R20="Do",E20,IF(R20="Delegate",$B$5,IF(R20="Escalate",$C$5,$D$5)))) | U20: =IF(AND(B20="Risk",R20="Defer"),-10,0) -> 0
A21: Grup chat ramai 80 pesan | B21: Execution | C21: Defer | D21: Delegate | E21: 30 | G21: =IF(F21="","",IF(F21=C21,10,IF(F21=D21,5,0))) | H21: =IF(F21="","",IF(F21="Do",E21,IF(F21="Delegate",$B$5,IF(F21="Escalate",$C$5,$D$5)))) | I21: =IF(AND(B21="Risk",F21="Defer"),-10,0) -> 0 | K21: =IF(J21="","",IF(J21=C21,10,IF(J21=D21,5,0))) | L21: =IF(J21="","",IF(J21="Do",E21,IF(J21="Delegate",$B$5,IF(J21="Escalate",$C$5,$D$5)))) | M21: =IF(AND(B21="Risk",J21="Defer"),-10,0) -> 0 | O21: =IF(N21="","",IF(N21=C21,10,IF(N21=D21,5,0))) | P21: =IF(N21="","",IF(N21="Do",E21,IF(N21="Delegate",$B$5,IF(N21="Escalate",$C$5,$D$5)))) | Q21: =IF(AND(B21="Risk",N21="Defer"),-10,0) -> 0 | S21: =IF(R21="","",IF(R21=C21,10,IF(R21=D21,5,0))) | T21: =IF(R21="","",IF(R21="Do",E21,IF(R21="Delegate",$B$5,IF(R21="Escalate",$C$5,$D$5)))) | U21: =IF(AND(B21="Risk",R21="Defer"),-10,0) -> 0
A22: Staf terbaik ingin resign | B22: People | C22: Do | D22: Escalate | E22: 45 | G22: =IF(F22="","",IF(F22=C22,10,IF(F22=D22,5,0))) | H22: =IF(F22="","",IF(F22="Do",E22,IF(F22="Delegate",$B$5,IF(F22="Escalate",$C$5,$D$5)))) | I22: =IF(AND(B22="Risk",F22="Defer"),-10,0) -> 0 | K22: =IF(J22="","",IF(J22=C22,10,IF(J22=D22,5,0))) | L22: =IF(J22="","",IF(J22="Do",E22,IF(J22="Delegate",$B$5,IF(J22="Escalate",$C$5,$D$5)))) | M22: =IF(AND(B22="Risk",J22="Defer"),-10,0) -> 0 | O22: =IF(N22="","",IF(N22=C22,10,IF(N22=D22,5,0))) | P22: =IF(N22="","",IF(N22="Do",E22,IF(N22="Delegate",$B$5,IF(N22="Escalate",$C$5,$D$5)))) | Q22: =IF(AND(B22="Risk",N22="Defer"),-10,0) -> 0 | S22: =IF(R22="","",IF(R22=C22,10,IF(R22=D22,5,0))) | T22: =IF(R22="","",IF(R22="Do",E22,IF(R22="Delegate",$B$5,IF(R22="Escalate",$C$5,$D$5)))) | U22: =IF(AND(B22="Risk",R22="Defer"),-10,0) -> 0
A23: Approval kredit menumpuk 6 berkas | B23: Business | C23: Do | D23: Delegate | E23: 60 | G23: =IF(F23="","",IF(F23=C23,10,IF(F23=D23,5,0))) | H23: =IF(F23="","",IF(F23="Do",E23,IF(F23="Delegate",$B$5,IF(F23="Escalate",$C$5,$D$5)))) | I23: =IF(AND(B23="Risk",F23="Defer"),-10,0) -> 0 | K23: =IF(J23="","",IF(J23=C23,10,IF(J23=D23,5,0))) | L23: =IF(J23="","",IF(J23="Do",E23,IF(J23="Delegate",$B$5,IF(J23="Escalate",$C$5,$D$5)))) | M23: =IF(AND(B23="Risk",J23="Defer"),-10,0) -> 0 | O23: =IF(N23="","",IF(N23=C23,10,IF(N23=D23,5,0))) | P23: =IF(N23="","",IF(N23="Do",E23,IF(N23="Delegate",$B$5,IF(N23="Escalate",$C$5,$D$5)))) | Q23: =IF(AND(B23="Risk",N23="Defer"),-10,0) -> 0 | S23: =IF(R23="","",IF(R23=C23,10,IF(R23=D23,5,0))) | T23: =IF(R23="","",IF(R23="Do",E23,IF(R23="Delegate",$B$5,IF(R23="Escalate",$C$5,$D$5)))) | U23: =IF(AND(B23="Risk",R23="Defer"),-10,0) -> 0
... A26: Coaching terjadwal 30 menit | B26: People | C26: Do | D26: Defer | E26: 30 | G26: =IF(F26="","",IF(F26=C26,10,IF(F26=D26,5,0))) | H26: =IF(F26="","",IF(F26="Do",E26,IF(F26="Delegate",$B$5,IF(F26="Escalate",$C$5,$D$5)))) | I26: =IF(AND(B26="Risk",F26="Defer"),-10,0) -> 0 | K26: =IF(J26="","",IF(J26=C26,10,IF(J26=D26,5,0))) | L26: =IF(J26="","",IF(J26="Do",E26,IF(J26="Delegate",$B$5,IF(J26="Escalate",$C$5,$D$5)))) | M26: =IF(AND(B26="Risk",J26="Defer"),-10,0) -> 0 | O26: =IF(N26="","",IF(N26=C26,10,IF(N26=D26,5,0))) | P26: =IF(N26="","",IF(N26="Do",E26,IF(N26="Delegate",$B$5,IF(N26="Escalate",$C$5,$D$5)))) | Q26: =IF(AND(B26="Risk",N26="Defer"),-10,0) -> 0 | S26: =IF(R26="","",IF(R26=C26,10,IF(R26=D26,5,0))) | T26: =IF(R26="","",IF(R26="Do",E26,IF(R26="Delegate",$B$5,IF(R26="Escalate",$C$5,$D$5)))) | U26: =IF(AND(B26="Risk",R26="Defer"),-10,0) -> 0
A28: Ringkasan | F28: Tim 1 | J28: Tim 2 | N28: Tim 3 | R28: Tim 4
A29: Business | F29: =SUMIFS(G7:G26,$B$7:$B$26,"Business") -> 10 | J29: =SUMIFS(K7:K26,$B$7:$B$26,"Business") -> 10 | N29: =SUMIFS(O7:O26,$B$7:$B$26,"Business") -> 0 | R29: =SUMIFS(S7:S26,$B$7:$B$26,"Business") -> 0
A30: Customer | F30: =SUMIFS(G7:G26,$B$7:$B$26,"Customer") -> 10 | J30: =SUMIFS(K7:K26,$B$7:$B$26,"Customer") -> 10 | N30: =SUMIFS(O7:O26,$B$7:$B$26,"Customer") -> 0 | R30: =SUMIFS(S7:S26,$B$7:$B$26,"Customer") -> 0
A31: Risk | F31: =SUMIFS(G7:G26,$B$7:$B$26,"Risk") -> 20 | J31: =SUMIFS(K7:K26,$B$7:$B$26,"Risk") -> 5 | N31: =SUMIFS(O7:O26,$B$7:$B$26,"Risk") -> 0 | R31: =SUMIFS(S7:S26,$B$7:$B$26,"Risk") -> 0
A32: People | F32: =SUMIFS(G7:G26,$B$7:$B$26,"People") -> 10 | J32: =SUMIFS(K7:K26,$B$7:$B$26,"People") -> 5 | N32: =SUMIFS(O7:O26,$B$7:$B$26,"People") -> 0 | R32: =SUMIFS(S7:S26,$B$7:$B$26,"People") -> 0
A33: Execution | F33: =SUMIFS(G7:G26,$B$7:$B$26,"Execution") -> 0 | J33: =SUMIFS(K7:K26,$B$7:$B$26,"Execution") -> 0 | N33: =SUMIFS(O7:O26,$B$7:$B$26,"Execution") -> 0 | R33: =SUMIFS(S7:S26,$B$7:$B$26,"Execution") -> 0
A34: Total menit | F34: =SUM(H7:H26) -> 160 | J34: =SUM(L7:L26) -> 120 | N34: =SUM(P7:P26) -> 0 | R34: =SUM(T7:T26) -> 0
A35: Risk Penalty | F35: =SUM(I7:I26) -> 0 | J35: =SUM(M7:M26) -> -10 | N35: =SUM(Q7:Q26) -> 0 | R35: =SUM(U7:U26) -> 0
A36: Execution Penalty | F36: =IF(F34>480,-15,0)+IF(COUNTIF(F7:F26,"Escalate")+COUNTIF(F7:F26,"Defer")>8,-10,0) -> 0 | J36: =IF(J34>480,-15,0)+IF(COUNTIF(J7:J26,"Escalate")+COUNTIF(J7:J26,"Defer")>8,-10,0) -> 0 | N36: =IF(N34>480,-15,0)+IF(COUNTIF(N7:N26,"Escalate")+COUNTIF(N7:N26,"Defer")>8,-10,0) -> 0 | R36: =IF(R34>480,-15,0)+IF(COUNTIF(R7:R26,"Escalate")+COUNTIF(R7:R26,"Defer")>8,-10,0) -> 0
A37: TOTAL SKOR | F37: =SUM(F29:F33)+F35+F36 -> 50 | J37: =SUM(J29:J33)+J35+J36 -> 20 | N37: =SUM(N29:N33)+N35+N36 -> 0 | R37: =SUM(R29:R33)+R35+R36 -> 0
A38: Balance Index (min/max) | F38: =IFERROR(MIN(F29:F33)/MAX(F29:F33),0) -> 0 | J38: =IFERROR(MIN(J29:J33)/MAX(J29:J33),0) -> 0 | N38: =IFERROR(MIN(N29:N33)/MAX(N29:N33),0) -> 0 | R38: =IFERROR(MIN(R29:R33)/MAX(R29:R33),0) -> 0
A40: Aturan: Best +10, Acceptable +5. Defer pada kejadian Risk −10. Menit > 480 = −15. Escalate+Defer > 8 kali = −10 (terlalu hati-hati). Contoh pilihan Tim 1–2 baris awal boleh dihapus.

Sheet 16 Decision Auction
A1: Game 10 · The Decision Auction
A2: Isi 1 untuk program yang dipilih tiap ronde (maks 3, budget 1.000). Info ronde mengubah benefit (faktor bisa diubah trainer).
A3: Legenda: sel kuning = diisi peserta/trainer (teks biru); sel putih/abu = otomatis (rumus) atau panduan.
A4: Budget | B4: 1000 | C4: Biaya switching | D4: 0.1
A6: Program | B6: Cost | C6: Benefit dasar | D6: Risk 1–3 | E6: Uncert. 1–3 | F6: Faktor R1 | G6: Faktor R2 | H6: Faktor R3 | I6: T1 R0 | J6: R1 | K6: R2 | L6: R3 | M6: T2 R0 | N6: R1 | O6: R2 | P6: R3 | Q6: T3 R0 | R6: R1 | S6: R2 | T6: R3 | U6: T4 R0 | V6: R1 | W6: R2 | X6: R3 | Y6: Benefit akhir
A7: Hire staff | B7: 300 | C7: 350 | D7: 1 | E7: 1 | F7: 1 | G7: 1 | H7: 1.4 | Y7: =C7*F7*G7*H7 -> 490
A8: Automation | B8: 450 | C8: 650 | D8: 2 | E8: 3 | F8: 0.4 | G8: 1 | H8: 1 | Y8: =C8*F8*G8*H8 -> 260
A9: Training | B9: 150 | C9: 220 | D9: 1 | E9: 2 | F9: 1 | G9: 1 | H9: 1.3 | I9: 1 | J9: 1 | K9: 1 | L9: 1 | Y9: =C9*F9*G9*H9 -> 286
A10: Process redesign | B10: 250 | C10: 420 | D10: 2 | E10: 2 | F10: 1 | G10: 1.1 | H10: 1 | I10: 1 | J10: 1 | K10: 1 | L10: 1 | Y10: =C10*F10*G10*H10 -> 462
A11: Marketing campaign | B11: 300 | C11: 380 | D11: 2 | E11: 3 | F11: 1 | G11: 0.8 | H11: 1 | Y11: =C11*F11*G11*H11 -> 304
A12: Collection improvement | B12: 200 | C12: 380 | D12: 1 | E12: 2 | F12: 1 | G12: 1.5 | H12: 1 | I12: 1 | J12: 1 | K12: 1 | L12: 1 | Y12: =C12*F12*G12*H12 -> 570
A13: System upgrade | B13: 500 | C13: 700 | D13: 3 | E13: 3 | F13: 0.7 | G13: 1 | H13: 1 | Y13: =C13*F13*G13*H13 -> 490
A14: Benefit akhir (setelah R3)
A16: Info R1 | B16: Vendor otomasi terlambat 6 bulan; upgrade sistem tertunda.
A17: Info R2 | B17: NPL naik di segmen mikro.
A18: Info R3 | B18: Dua staf senior resign.
A20: Ringkasan per tim | I20: Tim 1 | M20: Tim 2 | Q20: Tim 3 | U20: Tim 4
A21: Biaya R0 | I21: =SUMPRODUCT($B$7:$B$13,--(I7:I13=1)) -> 600 | M21: =SUMPRODUCT($B$7:$B$13,--(M7:M13=1)) -> 0 | Q21: =SUMPRODUCT($B$7:$B$13,--(Q7:Q13=1)) -> 0 | U21: =SUMPRODUCT($B$7:$B$13,--(U7:U13=1)) -> 0
A22: Biaya R3 | I22: =SUMPRODUCT($B$7:$B$13,--(L7:L13=1)) -> 600 | M22: =SUMPRODUCT($B$7:$B$13,--(P7:P13=1)) -> 0 | Q22: =SUMPRODUCT($B$7:$B$13,--(T7:T13=1)) -> 0 | U22: =SUMPRODUCT($B$7:$B$13,--(X7:X13=1)) -> 0
A23: Jumlah program R3 | I23: =COUNTIF(L7:L13,1) -> 3 | M23: =COUNTIF(P7:P13,1) -> 0 | Q23: =COUNTIF(T7:T13,1) -> 0 | U23: =COUNTIF(X7:X13,1) -> 0
A24: Cek aturan R3 | I24: =IF(AND(I22<=$B$4,I23<=3),"OK","Melanggar") -> OK | M24: =IF(AND(M22<=$B$4,M23<=3),"OK","Melanggar") -> OK | Q24: =IF(AND(Q22<=$B$4,Q23<=3),"OK","Melanggar") -> OK | U24: =IF(AND(U22<=$B$4,U23<=3),"OK","Melanggar") -> OK
A25: Biaya switching total | I25: =(SUMPRODUCT($B$7:$B$13,--(I7:I13=1),--(J7:J13<>1))+SUMPRODUCT($B$7:$B$13,--(J7:J13=1),--(K7:K13<>1))+SUMPRODUCT($B$7:$B$13,--(K7:K13=1),--(L7:L13<>1)))*$D$4 -> 0 | M25: =(SUMPRODUCT($B$7:$B$13,--(M7:M13=1),--(N7:N13<>1))+SUMPRODUCT($B$7:$B$13,--(N7:N13=1),--(O7:O13<>1))+SUMPRODUCT($B$7:$B$13,--(O7:O13=1),--(P7:P13<>1)))*$D$4 -> 0 | Q25: =(SUMPRODUCT($B$7:$B$13,--(Q7:Q13=1),--(R7:R13<>1))+SUMPRODUCT($B$7:$B$13,--(R7:R13=1),--(S7:S13<>1))+SUMPRODUCT($B$7:$B$13,--(S7:S13=1),--(T7:T13<>1)))*$D$4 -> 0 | U25: =(SUMPRODUCT($B$7:$B$13,--(U7:U13=1),--(V7:V13<>1))+SUMPRODUCT($B$7:$B$13,--(V7:V13=1),--(W7:W13<>1))+SUMPRODUCT($B$7:$B$13,--(W7:W13=1),--(X7:X13<>1)))*$D$4 -> 0
A26: Benefit akhir | I26: =SUMPRODUCT($Y$7:$Y$13,--(L7:L13=1)) -> 1318 | M26: =SUMPRODUCT($Y$7:$Y$13,--(P7:P13=1)) -> 0 | Q26: =SUMPRODUCT($Y$7:$Y$13,--(T7:T13=1)) -> 0 | U26: =SUMPRODUCT($Y$7:$Y$13,--(X7:X13=1)) -> 0
A27: Exposure risiko | I27: =SUMPRODUCT($D$7:$D$13,--(L7:L13=1)) -> 4 | M27: =SUMPRODUCT($D$7:$D$13,--(P7:P13=1)) -> 0 | Q27: =SUMPRODUCT($D$7:$D$13,--(T7:T13=1)) -> 0 | U27: =SUMPRODUCT($D$7:$D$13,--(X7:X13=1)) -> 0
A28: NET SCORE | I28: =IF(I24="OK",I26-I25-I22,0) -> 718 | M28: =IF(M24="OK",M26-M25-M22,0) -> 0 | Q28: =IF(Q24="OK",Q26-Q25-Q22,0) -> 0 | U28: =IF(U24="OK",U26-U25-U22,0) -> 0
A30: NET SCORE = benefit akhir − biaya program − biaya switching. Pelanggaran aturan (budget/maks 3) = 0.

Sheet 17 War Room Score
A1: Leadership Scorecard · War Room (100 poin)
A2: Observer mengisi skor per dimensi (0–maks). Total, peringkat, dan dimensi terlemah dihitung otomatis.
A3: Legenda: sel kuning = diisi peserta/trainer (teks biru); sel putih/abu = otomatis (rumus) atau panduan.
A5: Dimensi | B5: Maks | C5: Rendah | D5: Sedang | E5: Tinggi | F5: Tim 1 | G5: Tim 2 | H5: Tim 3 | I5: Tim 4 | J5: Tim 5 | K5: Tim 6
A6: Self Leadership | B6: 10 | C6: Panik, saling menyalahkan | D6: Tenang, sebagian ownership | E6: Tenang, ownership jelas, accountable
A7: Priority | B7: 15 | C7: Semua dikerjakan bersamaan | D7: Prioritas ada, tidak diperbarui | E7: P1–P4 jelas & diperbarui tiap event
A8: Time Management | B8: 10 | C8: Melewati timebox | D8: Timebox sebagian | E8: Timebox disiplin, ada buffer
A9: Critical Thinking | B9: 20 | C9: Menyimpulkan tanpa data | D9: Sebagian berbasis evidence | E9: Fakta vs asumsi dipisah, root cause dicari
A10: Decision Quality | B10: 15 | C10: Satu opsi, tanpa trade-off | D10: Opsi ada, trade-off lemah | E10: ≥3 opsi, trade-off & reversibility dinilai
A11: Risk Awareness | B11: 10 | C11: Fraud/compliance ditunda | D11: Risiko dicatat, tidak dieskalasi | E11: Eskalasi tepat waktu ke fungsi terkait
A12: Delegation | B12: 10 | C12: Semua dikerjakan pimpinan | D12: Delegasi tanpa outcome jelas | E12: Delegation contract & RACI jelas
A13: Execution | B13: 10 | C13: Tanpa action tracker | D13: Tracker tanpa owner/evidence | E13: Owner, deadline, evidence, checkpoint lengkap
A14: TOTAL | B14: =SUM(B6:B13) -> 100 | F14: =IF(COUNT(F6:F13)=0,"",SUM(F6:F13)) | G14: =IF(COUNT(G6:G13)=0,"",SUM(G6:G13)) | H14: =IF(COUNT(H6:H13)=0,"",SUM(H6:H13)) | I14: =IF(COUNT(I6:I13)=0,"",SUM(I6:I13)) | J14: =IF(COUNT(J6:J13)=0,"",SUM(J6:J13)) | K14: =IF(COUNT(K6:K13)=0,"",SUM(K6:K13))
A15: Peringkat | F15: =IF(F14="","",RANK(F14,$F$14:$K$14)) | G15: =IF(G14="","",RANK(G14,$F$14:$K$14)) | H15: =IF(H14="","",RANK(H14,$F$14:$K$14)) | I15: =IF(I14="","",RANK(I14,$F$14:$K$14)) | J15: =IF(J14="","",RANK(J14,$F$14:$K$14)) | K15: =IF(K14="","",RANK(K14,$F$14:$K$14))
A16: Dimensi terlemah (%) | F16: =IF(COUNT(F19:F26)<8,"",INDEX($A$19:$A$26,MATCH(MIN(F19:F26),F19:F26,0))) | G16: =IF(COUNT(G19:G26)<8,"",INDEX($A$19:$A$26,MATCH(MIN(G19:G26),G19:G26,0))) | H16: =IF(COUNT(H19:H26)<8,"",INDEX($A$19:$A$26,MATCH(MIN(H19:H26),H19:H26,0))) | I16: =IF(COUNT(I19:I26)<8,"",INDEX($A$19:$A$26,MATCH(MIN(I19:I26),I19:I26,0))) | J16: =IF(COUNT(J19:J26)<8,"",INDEX($A$19:$A$26,MATCH(MIN(J19:J26),J19:J26,0))) | K16: =IF(COUNT(K19:K26)<8,"",INDEX($A$19:$A$26,MATCH(MIN(K19:K26),K19:K26,0)))
A18: Skor normal (% dari maks)
A19: Self Leadership | F19: =IF(F6="","",F6/$B$6) | G19: =IF(G6="","",G6/$B$6) | H19: =IF(H6="","",H6/$B$6) | I19: =IF(I6="","",I6/$B$6) | J19: =IF(J6="","",J6/$B$6) | K19: =IF(K6="","",K6/$B$6)
A20: Priority | F20: =IF(F7="","",F7/$B$7) | G20: =IF(G7="","",G7/$B$7) | H20: =IF(H7="","",H7/$B$7) | I20: =IF(I7="","",I7/$B$7) | J20: =IF(J7="","",J7/$B$7) | K20: =IF(K7="","",K7/$B$7)
A21: Time Management | F21: =IF(F8="","",F8/$B$8) | G21: =IF(G8="","",G8/$B$8) | H21: =IF(H8="","",H8/$B$8) | I21: =IF(I8="","",I8/$B$8) | J21: =IF(J8="","",J8/$B$8) | K21: =IF(K8="","",K8/$B$8)
A22: Critical Thinking | F22: =IF(F9="","",F9/$B$9) | G22: =IF(G9="","",G9/$B$9) | H22: =IF(H9="","",H9/$B$9) | I22: =IF(I9="","",I9/$B$9) | J22: =IF(J9="","",J9/$B$9) | K22: =IF(K9="","",K9/$B$9)
A23: Decision Quality | F23: =IF(F10="","",F10/$B$10) | G23: =IF(G10="","",G10/$B$10) | H23: =IF(H10="","",H10/$B$10) | I23: =IF(I10="","",I10/$B$10) | J23: =IF(J10="","",J10/$B$10) | K23: =IF(K10="","",K10/$B$10)
A24: Risk Awareness | F24: =IF(F11="","",F11/$B$11) | G24: =IF(G11="","",G11/$B$11) | H24: =IF(H11="","",H11/$B$11) | I24: =IF(I11="","",I11/$B$11) | J24: =IF(J11="","",J11/$B$11) | K24: =IF(K11="","",K11/$B$11)
A25: Delegation | F25: =IF(F12="","",F12/$B$12) | G25: =IF(G12="","",G12/$B$12) | H25: =IF(H12="","",H12/$B$12) | I25: =IF(I12="","",I12/$B$12) | J25: =IF(J12="","",J12/$B$12) | K25: =IF(K12="","",K12/$B$12)
A26: Execution | F26: =IF(F13="","",F13/$B$13) | G26: =IF(G13="","",G13/$B$13) | H26: =IF(H13="","",H13/$B$13) | I26: =IF(I13="","",I13/$B$13) | J26: =IF(J13="","",J13/$B$13) | K26: =IF(K13="","",K13/$B$13)

Sheet 18 Boardroom Rubric
A1: Game 11 · 60-Second Boardroom Rubric
A2: Skor 1–5 per kriteria. Maks 30.
A3: Legenda: sel kuning = diisi peserta/trainer (teks biru); sel putih/abu = otomatis (rumus) atau panduan.
A5: Presenter | B5: Clarity | C5: Logic | D5: Evidence | E5: Risk Awareness | F5: Recommendation | G5: Action | H5: Total /30 | I5: % | J5: Kategori
H6: =IF(COUNT(B6:G6)<6,"",SUM(B6:G6)) | I6: =IF(H6="","",H6/30) | J6: =IF(I6="","",IF(I6>=0.8,"Boardroom-ready",IF(I6>=0.6,"Berkembang","Perlu latihan")))
H7: =IF(COUNT(B7:G7)<6,"",SUM(B7:G7)) | I7: =IF(H7="","",H7/30) | J7: =IF(I7="","",IF(I7>=0.8,"Boardroom-ready",IF(I7>=0.6,"Berkembang","Perlu latihan")))
H8: =IF(COUNT(B8:G8)<6,"",SUM(B8:G8)) | I8: =IF(H8="","",H8/30) | J8: =IF(I8="","",IF(I8>=0.8,"Boardroom-ready",IF(I8>=0.6,"Berkembang","Perlu latihan")))
H9: =IF(COUNT(B9:G9)<6,"",SUM(B9:G9)) | I9: =IF(H9="","",H9/30) | J9: =IF(I9="","",IF(I9>=0.8,"Boardroom-ready",IF(I9>=0.6,"Berkembang","Perlu latihan")))
H10: =IF(COUNT(B10:G10)<6,"",SUM(B10:G10)) | I10: =IF(H10="","",H10/30) | J10: =IF(I10="","",IF(I10>=0.8,"Boardroom-ready",IF(I10>=0.6,"Berkembang","Perlu latihan")))
H11: =IF(COUNT(B11:G11)<6,"",SUM(B11:G11)) | I11: =IF(H11="","",H11/30) | J11: =IF(I11="","",IF(I11>=0.8,"Boardroom-ready",IF(I11>=0.6,"Berkembang","Perlu latihan")))
H12: =IF(COUNT(B12:G12)<6,"",SUM(B12:G12)) | I12: =IF(H12="","",H12/30) | J12: =IF(I12="","",IF(I12>=0.8,"Boardroom-ready",IF(I12>=0.6,"Berkembang","Perlu latihan")))
H13: =IF(COUNT(B13:G13)<6,"",SUM(B13:G13)) | I13: =IF(H13="","",H13/30) | J13: =IF(I13="","",IF(I13>=0.8,"Boardroom-ready",IF(I13>=0.6,"Berkembang","Perlu latihan")))
H14: =IF(COUNT(B14:G14)<6,"",SUM(B14:G14)) | I14: =IF(H14="","",H14/30) | J14: =IF(I14="","",IF(I14>=0.8,"Boardroom-ready",IF(I14>=0.6,"Berkembang","Perlu latihan")))
H15: =IF(COUNT(B15:G15)<6,"",SUM(B15:G15)) | I15: =IF(H15="","",H15/30) | J15: =IF(I15="","",IF(I15>=0.8,"Boardroom-ready",IF(I15>=0.6,"Berkembang","Perlu latihan")))
H16: =IF(COUNT(B16:G16)<6,"",SUM(B16:G16)) | I16: =IF(H16="","",H16/30) | J16: =IF(I16="","",IF(I16>=0.8,"Boardroom-ready",IF(I16>=0.6,"Berkembang","Perlu latihan")))
H17: =IF(COUNT(B17:G17)<6,"",SUM(B17:G17)) | I17: =IF(H17="","",H17/30) | J17: =IF(I17="","",IF(I17>=0.8,"Boardroom-ready",IF(I17>=0.6,"Berkembang","Perlu latihan")))
... H35: =IF(COUNT(B35:G35)<6,"",SUM(B35:G35)) | I35: =IF(H35="","",H35/30) | J35: =IF(I35="","",IF(I35>=0.8,"Boardroom-ready",IF(I35>=0.6,"Berkembang","Perlu latihan")))

Sheet 19 Pre-Post Test
A1: Pre-Test & Post-Test (20 soal pilihan ganda)
A2: Soal sama untuk Pre & Post. Kunci di kolom G (sembunyikan/lindungi sebelum dibagikan). Jawaban peserta diisi di sheet 19b.
A3: Legenda: sel kuning = diisi peserta/trainer (teks biru); sel putih/abu = otomatis (rumus) atau panduan.
A5: No | B5: Pertanyaan | C5: A | D5: B | E5: C | F5: D | G5: Kunci
A6: 1 | B6: Pekerjaan penting tetapi tidak mendesak (mis. coaching tim) masuk kuadran Eisenhower… | C6: DO | D6: PLAN | E6: DELEGATE | F6: ELIMINATE | G6: B
A7: 2 | B7: Dalam Banking Priority Scorecard, pekerjaan dengan Risk/Compliance Impact = 5 otomatis menjadi… | C7: P4 | D7: P3 | E7: P2 | F7: P1 | G7: D
A8: 3 | B8: Porsi buffer yang dianjurkan dari total jam kerja mingguan adalah… | C8: 0–5% | D8: 15–20% | E8: 30–40% | F8: 50% | G8: B
A9: 4 | B9: "Nasabah ini aman karena sudah 15 tahun menjadi nasabah" adalah contoh… | C9: Assumption | D9: Fact | E9: Evidence | F9: Conclusion | G9: A
A10: 5 | B10: Elemen Delegation Contract yang memastikan pekerjaan bisa dinyatakan selesai adalah… | C10: Why | D10: Boundary | E10: Evidence | F10: Authority | G10: C
A11: 6 | B11: Level delegasi ketika staf boleh memutuskan lalu menginformasikan ke atasan adalah… | C11: L2 Analyze | D11: L3 Recommend | E11: L5 Own | F11: L4 Decide & inform | G11: D
A12: 7 | B12: Pada GROW, tahap "Apa yang sudah terjadi sejauh ini?" termasuk… | C12: Reality | D12: Goal | E12: Options | F12: Way Forward | G12: A
A13: 8 | B13: Contoh feedback SBI yang tepat adalah… | C13: "Kamu kurang teliti." | D13: "Pada laporan kemarin, dua angka belum direkonsiliasi sehingga review diulang." | E13: "Tolong lebih baik lagi ya." | F13: "Kinerja kamu mengecewakan." | G13: B
A14: 9 | B14: Tujuan utama teknik 5 Whys adalah… | C14: Mencari pihak yang salah | D14: Mempercepat rapat | E14: Menembus symptom menuju root cause | F14: Membuat daftar solusi | G14: C
A15: 10 | B15: Yang BUKAN kategori fishbone dalam training ini adalah… | C15: People | D15: Process | E15: Data | F15: Luck | G15: D
A16: 11 | B16: Memilih opsi karena "Direktur menyukai opsi A" tanpa menguji data adalah… | C16: Authority bias | D16: Anchoring | E16: Recency bias | F16: Sunk cost | G16: A
A17: 12 | B17: Terus mendanai proyek gagal karena "sudah terlanjur keluar biaya besar" adalah… | C17: Halo effect | D17: Groupthink | E17: Sunk cost | F17: Availability bias | G17: C
... A25: 20 | B25: Cara terbaik membuktikan training berdampak adalah… | C25: Skor kepuasan peserta | D25: Metrik perilaku before vs after | E25: Jumlah slide | F25: Durasi training | G25: B

Sheet 19b Test Scoring
A1: Pre/Post Test · Lembar Skor Otomatis
A2: Ketik jawaban A–D per soal. Skor = jumlah benar × 5 (maks 100). Gain = Post − Pre.
A3: Legenda: sel kuning = diisi peserta/trainer (teks biru); sel putih/abu = otomatis (rumus) atau panduan.
A5: No | B5: Nama Peserta | C5: Tes | D5: 1 | E5: 2 | F5: 3 | G5: 4 | H5: 5 | I5: 6 | J5: 7 | K5: 8 | L5: 9 | M5: 10 | N5: 11 | O5: 12 | P5: 13 | Q5: 14 | R5: 15 | S5: 16 | T5: 17 | U5: 18 | V5: 19 | W5: 20 | X5: Skor
B6: KUNCI | D6: ='19 Pre-Post Test'!G6 -> B | E6: ='19 Pre-Post Test'!G7 -> D | F6: ='19 Pre-Post Test'!G8 -> B | G6: ='19 Pre-Post Test'!G9 -> A | H6: ='19 Pre-Post Test'!G10 -> C | I6: ='19 Pre-Post Test'!G11 -> D | J6: ='19 Pre-Post Test'!G12 -> A | K6: ='19 Pre-Post Test'!G13 -> B | L6: ='19 Pre-Post Test'!G14 -> C | M6: ='19 Pre-Post Test'!G15 -> D | N6: ='19 Pre-Post Test'!G16 -> A | O6: ='19 Pre-Post Test'!G17 -> C | P6: ='19 Pre-Post Test'!G18 -> B | Q6: ='19 Pre-Post Test'!G19 -> C | R6: ='19 Pre-Post Test'!G20 -> D | S6: ='19 Pre-Post Test'!G21 -> A | T6: ='19 Pre-Post Test'!G22 -> B | U6: ='19 Pre-Post Test'!G23 -> C | V6: ='19 Pre-Post Test'!G24 -> D | W6: ='19 Pre-Post Test'!G25 -> B
A7: 1 | C7: Pre | X7: =IF(COUNTA(D7:W7)=0,"",SUMPRODUCT(--(UPPER(D7:W7)=$D$6:$W$6))*5)
B8: =B7 -> 0 | C8: Post | X8: =IF(COUNTA(D8:W8)=0,"",SUMPRODUCT(--(UPPER(D8:W8)=$D$6:$W$6))*5)
A9: 2 | C9: Pre | X9: =IF(COUNTA(D9:W9)=0,"",SUMPRODUCT(--(UPPER(D9:W9)=$D$6:$W$6))*5)
B10: =B9 -> 0 | C10: Post | X10: =IF(COUNTA(D10:W10)=0,"",SUMPRODUCT(--(UPPER(D10:W10)=$D$6:$W$6))*5)
A11: 3 | C11: Pre | X11: =IF(COUNTA(D11:W11)=0,"",SUMPRODUCT(--(UPPER(D11:W11)=$D$6:$W$6))*5)
B12: =B11 -> 0 | C12: Post | X12: =IF(COUNTA(D12:W12)=0,"",SUMPRODUCT(--(UPPER(D12:W12)=$D$6:$W$6))*5)
A13: 4 | C13: Pre | X13: =IF(COUNTA(D13:W13)=0,"",SUMPRODUCT(--(UPPER(D13:W13)=$D$6:$W$6))*5)
B14: =B13 -> 0 | C14: Post | X14: =IF(COUNTA(D14:W14)=0,"",SUMPRODUCT(--(UPPER(D14:W14)=$D$6:$W$6))*5)
A15: 5 | C15: Pre | X15: =IF(COUNTA(D15:W15)=0,"",SUMPRODUCT(--(UPPER(D15:W15)=$D$6:$W$6))*5)
B16: =B15 -> 0 | C16: Post | X16: =IF(COUNTA(D16:W16)=0,"",SUMPRODUCT(--(UPPER(D16:W16)=$D$6:$W$6))*5)
A17: 6 | C17: Pre | X17: =IF(COUNTA(D17:W17)=0,"",SUMPRODUCT(--(UPPER(D17:W17)=$D$6:$W$6))*5)
B18: =B17 -> 0 | C18: Post | X18: =IF(COUNTA(D18:W18)=0,"",SUMPRODUCT(--(UPPER(D18:W18)=$D$6:$W$6))*5)
A19: 7 | C19: Pre | X19: =IF(COUNTA(D19:W19)=0,"",SUMPRODUCT(--(UPPER(D19:W19)=$D$6:$W$6))*5)
B20: =B19 -> 0 | C20: Post | X20: =IF(COUNTA(D20:W20)=0,"",SUMPRODUCT(--(UPPER(D20:W20)=$D$6:$W$6))*5)
A21: 8 | C21: Pre | X21: =IF(COUNTA(D21:W21)=0,"",SUMPRODUCT(--(UPPER(D21:W21)=$D$6:$W$6))*5)
B22: =B21 -> 0 | C22: Post | X22: =IF(COUNTA(D22:W22)=0,"",SUMPRODUCT(--(UPPER(D22:W22)=$D$6:$W$6))*5)
A23: 9 | C23: Pre | X23: =IF(COUNTA(D23:W23)=0,"",SUMPRODUCT(--(UPPER(D23:W23)=$D$6:$W$6))*5)
B24: =B23 -> 0 | C24: Post | X24: =IF(COUNTA(D24:W24)=0,"",SUMPRODUCT(--(UPPER(D24:W24)=$D$6:$W$6))*5)
A25: 10 | C25: Pre | X25: =IF(COUNTA(D25:W25)=0,"",SUMPRODUCT(--(UPPER(D25:W25)=$D$6:$W$6))*5)
B26: =B25 -> 0 | C26: Post | X26: =IF(COUNTA(D26:W26)=0,"",SUMPRODUCT(--(UPPER(D26:W26)=$D$6:$W$6))*5)
A27: 11 | C27: Pre | X27: =IF(COUNTA(D27:W27)=0,"",SUMPRODUCT(--(UPPER(D27:W27)=$D$6:$W$6))*5)
B28: =B27 -> 0 | C28: Post | X28: =IF(COUNTA(D28:W28)=0,"",SUMPRODUCT(--(UPPER(D28:W28)=$D$6:$W$6))*5)
A29: 12 | C29: Pre | X29: =IF(COUNTA(D29:W29)=0,"",SUMPRODUCT(--(UPPER(D29:W29)=$D$6:$W$6))*5)
B30: =B29 -> 0 | C30: Post | X30: =IF(COUNTA(D30:W30)=0,"",SUMPRODUCT(--(UPPER(D30:W30)=$D$6:$W$6))*5)
A31: 13 | C31: Pre | X31: =IF(COUNTA(D31:W31)=0,"",SUMPRODUCT(--(UPPER(D31:W31)=$D$6:$W$6))*5)
B32: =B31 -> 0 | C32: Post | X32: =IF(COUNTA(D32:W32)=0,"",SUMPRODUCT(--(UPPER(D32:W32)=$D$6:$W$6))*5)
A33: 14 | C33: Pre | X33: =IF(COUNTA(D33:W33)=0,"",SUMPRODUCT(--(UPPER(D33:W33)=$D$6:$W$6))*5)
B34: =B33 -> 0 | C34: Post | X34: =IF(COUNTA(D34:W34)=0,"",SUMPRODUCT(--(UPPER(D34:W34)=$D$6:$W$6))*5)
A35: 15 | C35: Pre | X35: =IF(COUNTA(D35:W35)=0,"",SUMPRODUCT(--(UPPER(D35:W35)=$D$6:$W$6))*5)
B36: =B35 -> 0 | C36: Post | X36: =IF(COUNTA(D36:W36)=0,"",SUMPRODUCT(--(UPPER(D36:W36)=$D$6:$W$6))*5)
A37: 16 | C37: Pre | X37: =IF(COUNTA(D37:W37)=0,"",SUMPRODUCT(--(UPPER(D37:W37)=$D$6:$W$6))*5)
B38: =B37 -> 0 | C38: Post | X38: =IF(COUNTA(D38:W38)=0,"",SUMPRODUCT(--(UPPER(D38:W38)=$D$6:$W$6))*5)
A39: 17 | C39: Pre | X39: =IF(COUNTA(D39:W39)=0,"",SUMPRODUCT(--(UPPER(D39:W39)=$D$6:$W$6))*5)
B40: =B39 -> 0 | C40: Post | X40: =IF(COUNTA(D40:W40)=0,"",SUMPRODUCT(--(UPPER(D40:W40)=$D$6:$W$6))*5)
A41: 18 | C41: Pre | X41: =IF(COUNTA(D41:W41)=0,"",SUMPRODUCT(--(UPPER(D41:W41)=$D$6:$W$6))*5)
B42: =B41 -> 0 | C42: Post | X42: =IF(COUNTA(D42:W42)=0,"",SUMPRODUCT(--(UPPER(D42:W42)=$D$6:$W$6))*5)
A43: 19 | C43: Pre | X43: =IF(COUNTA(D43:W43)=0,"",SUMPRODUCT(--(UPPER(D43:W43)=$D$6:$W$6))*5)
B44: =B43 -> 0 | C44: Post | X44: =IF(COUNTA(D44:W44)=0,"",SUMPRODUCT(--(UPPER(D44:W44)=$D$6:$W$6))*5)
A45: 20 | C45: Pre | X45: =IF(COUNTA(D45:W45)=0,"",SUMPRODUCT(--(UPPER(D45:W45)=$D$6:$W$6))*5)
B46: =B45 -> 0 | C46: Post | X46: =IF(COUNTA(D46:W46)=0,"",SUMPRODUCT(--(UPPER(D46:W46)=$D$6:$W$6))*5)
A47: 21 | C47: Pre | X47: =IF(COUNTA(D47:W47)=0,"",SUMPRODUCT(--(UPPER(D47:W47)=$D$6:$W$6))*5)
B48: =B47 -> 0 | C48: Post | X48: =IF(COUNTA(D48:W48)=0,"",SUMPRODUCT(--(UPPER(D48:W48)=$D$6:$W$6))*5)
A49: 22 | C49: Pre | X49: =IF(COUNTA(D49:W49)=0,"",SUMPRODUCT(--(UPPER(D49:W49)=$D$6:$W$6))*5)
B50: =B49 -> 0 | C50: Post | X50: =IF(COUNTA(D50:W50)=0,"",SUMPRODUCT(--(UPPER(D50:W50)=$D$6:$W$6))*5)
A51: 23 | C51: Pre | X51: =IF(COUNTA(D51:W51)=0,"",SUMPRODUCT(--(UPPER(D51:W51)=$D$6:$W$6))*5)
B52: =B51 -> 0 | C52: Post | X52: =IF(COUNTA(D52:W52)=0,"",SUMPRODUCT(--(UPPER(D52:W52)=$D$6:$W$6))*5)
A53: 24 | C53: Pre | X53: =IF(COUNTA(D53:W53)=0,"",SUMPRODUCT(--(UPPER(D53:W53)=$D$6:$W$6))*5)
B54: =B53 -> 0 | C54: Post | X54: =IF(COUNTA(D54:W54)=0,"",SUMPRODUCT(--(UPPER(D54:W54)=$D$6:$W$6))*5)
A55: 25 | C55: Pre | X55: =IF(COUNTA(D55:W55)=0,"",SUMPRODUCT(--(UPPER(D55:W55)=$D$6:$W$6))*5)
B56: =B55 -> 0 | C56: Post | X56: =IF(COUNTA(D56:W56)=0,"",SUMPRODUCT(--(UPPER(D56:W56)=$D$6:$W$6))*5)
B58: Ringkasan | D58: Rata Pre | F58: Rata Post | H58: Gain | J58: % peserta naik
D59: =IFERROR(AVERAGE(X7,X9,X11,X13,X15,X17,X19,X21,X23,X25,X27,X29,X31,X33,X35,X37,X39,X41,X43,X45,X47,X49,X51,X53,X55),"") | F59: =IFERROR(AVERAGE(X8,X10,X12,X14,X16,X18,X20,X22,X24,X26,X28,X30,X32,X34,X36,X38,X40,X42,X44,X46,X48,X50,X52,X54,X56),"") | H59: =IFERROR(F59-D59,"") | J59: =IFERROR(((N(X8)>N(X7))*(X8<>"")+(N(X10)>N(X9))*(X10<>"")+(N(X12)>N(X11))*(X12<>"")+(N(X14)>N(X13))*(X14<>"")+(N(X16)>N(X15))*(X16<>"")+(N(X18)>N(X17))*(X18<>"")+(N(X20)>N(X19))*(X20<>"")+(N(X22)>N(X21))*(X22<>"")+(N(X24)>N(X23))*(X24<>"")+(N(X26)>N(X25))*(X26<>"")+(N(X28)>N(X27))*(X28<>"")+(N(X30)>N(X29))*(X30<>"")+(N(X32)>N(X31))*(X32<>"")+(N(X34)>N(X33))*(X34<>"")+(N(X36)>N(X35))*(X36<>"")+(N(X38)>N(X37))*(X38<>"")+(N(X40)>N(X39))*(X40<>"")+(N(X42)>N(X41))*(X42<>"")+(N(X44)>N(X43))*(X44<>"")+(N(X46)>N(X45))*(X46<>"")+(N(X48)>N(X47))*(X48<>"")+(N(X50)>N(X49))*(X50<>"")+(N(X52)>N(X51))*(X52<>"")+(N(X54)>N(X53))*(X54<>"")+(N(X56)>N(X55))*(X56<>""))/COUNT(X8,X10,X12,X14,X16,X18,X20,X22,X24,X26,X28,X30,X32,X34,X36,X38,X40,X42,X44,X46,X48,X50,X52,X54,X56),"")

Sheet 20 30-Day Plan
A1: 30-Day Leadership Transformation Plan
A2: Pilih 3 behavioral target. Isi tanggal mulai — tanggal review D7/D14/D30 terhitung otomatis.
A3: Legenda: sel kuning = diisi peserta/trainer (teks biru); sel putih/abu = otomatis (rumus) atau panduan.
A4: Nama | C4: Atasan langsung
A5: Tanggal mulai
A6: D7 Self Review | B6: =IF(B5="","",B5+7)
A7: D14 Manager Check-in | B7: =IF(B5="","",B5+14)
A8: D30 Impact Review | B8: =IF(B5="","",B5+30)
A10: Elemen | B10: Target 1 | C10: Target 2 | D10: Target 3
A11: Behavioral target
A12: Current behavior
A13: Desired behavior
A14: Action (spesifik, mingguan)
A15: Measure (angka)
A16: Barrier
A17: Support needed
A18: Review date | B18: =B8 | C18: =B8 | D18: =B8
A20: Contoh
A21: Behavioral target | B21: Delegation
A22: Current behavior | B22: Semua laporan mingguan saya kerjakan sendiri
A23: Desired behavior | B23: Laporan disusun staf (L3), saya review
A24: Action (spesifik, mingguan) | B24: Kontrak delegasi dengan 2 staf; checkpoint Rabu
A25: Measure (angka) | B25: Jam saya untuk laporan: 6 → 2 jam/minggu
A26: Barrier | B26: Kualitas awal belum stabil
A27: Support needed | B27: Template laporan dari atasan
A28: Review date | B28: D30

Sheet 21 Manager Follow-up
A1: Manager Follow-up Guide · D7 / D14 / D30
A2: D7 diisi peserta (self review); D14 dan D30 diisi bersama atasan.
A3: Legenda: sel kuning = diisi peserta/trainer (teks biru); sel putih/abu = otomatis (rumus) atau panduan.
A5: Pertanyaan | B5: D7 Self Review | C5: D14 Manager Check-in | D5: D30 Impact Review
A6: 1. Apa perilaku yang berubah?
A7: 2. Apa hasilnya?
A8: 3. Apa contoh nyata?
A9: 4. Apa hambatan?
A10: 5. Apa behavioral target berikutnya?
A12: Progres target (0–100%)
A13: Status | B13: =IF(B12="","",IF(B12>=0.8,"On track",IF(B12>=0.5,"Perlu dorongan","Perlu intervensi"))) | C13: =IF(C12="","",IF(C12>=0.8,"On track",IF(C12>=0.5,"Perlu dorongan","Perlu intervensi"))) | D13: =IF(D12="","",IF(D12>=0.8,"On track",IF(D12>=0.5,"Perlu dorongan","Perlu intervensi")))
A15: Tips manager
A16: Tanya contoh nyata, bukan niat.
A17: Gunakan SBI saat memberi feedback.
A18: Gunakan GROW, jangan langsung memberi solusi.
A19: Akui progres kecil secara spesifik.
A20: Sepakati satu tindakan dan tanggal berikutnya.

Sheet 22 Impact Metrics
A1: Leadership Impact Metrics · Before vs After
A2: Isi baseline (sebelum training) dan nilai Day 30. Arah: Turun = lebih baik / Naik = lebih baik.
A3: Legenda: sel kuning = diisi peserta/trainer (teks biru); sel putih/abu = otomatis (rumus) atau panduan.
A5: Metrik | B5: Satuan | C5: Arah baik | D5: Baseline | E5: Day 30 | F5: % perubahan | G5: Membaik?
A6: Overdue task | B6: jumlah | C6: Turun | F6: =IF(OR(D6="",E6="",D6=0),"",(E6-D6)/D6) | G6: =IF(F6="","",IF(OR(AND(C6="Turun",E6<D6),AND(C6="Naik",E6>D6)),"Ya","Belum"))
A7: Decision turnaround time | B7: hari | C7: Turun | F7: =IF(OR(D7="",E7="",D7=0),"",(E7-D7)/D7) | G7: =IF(F7="","",IF(OR(AND(C7="Turun",E7<D7),AND(C7="Naik",E7>D7)),"Ya","Belum"))
A8: Unnecessary meeting hours | B8: jam/minggu | C8: Turun | F8: =IF(OR(D8="",E8="",D8=0),"",(E8-D8)/D8) | G8: =IF(F8="","",IF(OR(AND(C8="Turun",E8<D8),AND(C8="Naik",E8>D8)),"Ya","Belum"))
A9: Delegation frequency | B9: tugas/minggu | C9: Naik | F9: =IF(OR(D9="",E9="",D9=0),"",(E9-D9)/D9) | G9: =IF(F9="","",IF(OR(AND(C9="Turun",E9<D9),AND(C9="Naik",E9>D9)),"Ya","Belum"))
A10: Rework | B10: kali/bulan | C10: Turun | F10: =IF(OR(D10="",E10="",D10=0),"",(E10-D10)/D10) | G10: =IF(F10="","",IF(OR(AND(C10="Turun",E10<D10),AND(C10="Naik",E10>D10)),"Ya","Belum"))
A11: Escalation quality | B11: skor 1–5 | C11: Naik | F11: =IF(OR(D11="",E11="",D11=0),"",(E11-D11)/D11) | G11: =IF(F11="","",IF(OR(AND(C11="Turun",E11<D11),AND(C11="Naik",E11>D11)),"Ya","Belum"))
A12: Team follow-up | B12: kali/minggu | C12: Naik | F12: =IF(OR(D12="",E12="",D12=0),"",(E12-D12)/D12) | G12: =IF(F12="","",IF(OR(AND(C12="Turun",E12<D12),AND(C12="Naik",E12>D12)),"Ya","Belum"))
A13: Action closure rate | B13: % | C13: Naik | F13: =IF(OR(D13="",E13="",D13=0),"",(E13-D13)/D13) | G13: =IF(F13="","",IF(OR(AND(C13="Turun",E13<D13),AND(C13="Naik",E13>D13)),"Ya","Belum"))
A14: Focus time | B14: jam/minggu | C14: Naik | F14: =IF(OR(D14="",E14="",D14=0),"",(E14-D14)/D14) | G14: =IF(F14="","",IF(OR(AND(C14="Turun",E14<D14),AND(C14="Naik",E14>D14)),"Ya","Belum"))
A16: Jumlah metrik membaik | G16: =COUNTIF(G6:G14,"Ya")&" / "&COUNTA(D6:D14) -> 0 / 0

Sheet 23 AAR & SSC
A1: After Action Review & Stop–Start–Continue
A2: Gunakan setelah game, proyek, insiden, atau di akhir training.
A3: Legenda: sel kuning = diisi peserta/trainer (teks biru); sel putih/abu = otomatis (rumus) atau panduan.
A5: After Action Review
A6: Apa yang seharusnya terjadi?
A7: Apa yang sebenarnya terjadi?
A8: Mengapa ada perbedaan?
A9: Apa yang dipelajari / dilakukan berbeda?
A11: Stop – Start – Continue
A12: STOP — perilaku yang harus dihentikan
A13: START — perilaku baru yang dimulai
A14: CONTINUE — perilaku yang dipertahankan
... A22: What will I do differently on Monday?

Sheet 24 Kartu Game
A1: Kartu Game Siap Cetak (Game 1–11 + War Room)
A2: Cetak per blok, potong menjadi kartu. Kolom kunci hanya untuk trainer. Semua kasus fiktif untuk latihan.
A3: Legenda: sel kuning = diisi peserta/trainer (teks biru); sel putih/abu = otomatis (rumus) atau panduan.
A5: Game 1 · Leadership Mirror — kartu situasi (respon A–E dibacakan trainer)
A6: No | B6: Situasi | C6: A Reactive / B Control | D6: C Avoiding | E6: D Accountable / E Empowering
A7: 1 | B7: Deadline terlewat: laporan bulanan ke kantor pusat telat | C7: A: bereaksi emosional, menegur di depan umum · B: ambil alih dan kerjakan sendiri | D7: C: menunda, tunggu masalah hilang, tidak eskalasi | E7: D: akui, cari akar, tetapkan tindakan · E: beri ruang tim menyelesaikan, pantau
A8: 2 | B8: Staf salah input data nasabah | C8: A: bereaksi emosional, menegur di depan umum · B: ambil alih dan kerjakan sendiri | D8: C: menunda, tunggu masalah hilang, tidak eskalasi | E8: D: akui, cari akar, tetapkan tindakan · E: beri ruang tim menyelesaikan, pantau
A9: 3 | B9: Funding baru 70% di minggu ke-3 | C9: A: bereaksi emosional, menegur di depan umum · B: ambil alih dan kerjakan sendiri | D9: C: menunda, tunggu masalah hilang, tidak eskalasi | E9: D: akui, cari akar, tetapkan tindakan · E: beri ruang tim menyelesaikan, pantau
A10: 4 | B10: Nasabah komplain keras di banking hall | C10: A: bereaksi emosional, menegur di depan umum · B: ambil alih dan kerjakan sendiri | D10: C: menunda, tunggu masalah hilang, tidak eskalasi | E10: D: akui, cari akar, tetapkan tindakan · E: beri ruang tim menyelesaikan, pantau
A11: 5 | B11: Migrasi sistem mundur 2 minggu | C11: A: bereaksi emosional, menegur di depan umum · B: ambil alih dan kerjakan sendiri | D11: C: menunda, tunggu masalah hilang, tidak eskalasi | E11: D: akui, cari akar, tetapkan tindakan · E: beri ruang tim menyelesaikan, pantau
A12: 6 | B12: Audit finding lewat batas komitmen | C12: A: bereaksi emosional, menegur di depan umum · B: ambil alih dan kerjakan sendiri | D12: C: menunda, tunggu masalah hilang, tidak eskalasi | E12: D: akui, cari akar, tetapkan tindakan · E: beri ruang tim menyelesaikan, pantau
A13: 7 | B13: Dua senior officer saling menyalahkan | C13: A: bereaksi emosional, menegur di depan umum · B: ambil alih dan kerjakan sendiri | D13: C: menunda, tunggu masalah hilang, tidak eskalasi | E13: D: akui, cari akar, tetapkan tindakan · E: beri ruang tim menyelesaikan, pantau
A14: 8 | B14: Atasan minta data 1 jam lagi | C14: A: bereaksi emosional, menegur di depan umum · B: ambil alih dan kerjakan sendiri | D14: C: menunda, tunggu masalah hilang, tidak eskalasi | E14: D: akui, cari akar, tetapkan tindakan · E: beri ruang tim menyelesaikan, pantau
A15: 9 | B15: Staf berprestasi resign: merasa tidak berkembang | C15: A: bereaksi emosional, menegur di depan umum · B: ambil alih dan kerjakan sendiri | D15: C: menunda, tunggu masalah hilang, tidak eskalasi | E15: D: akui, cari akar, tetapkan tindakan · E: beri ruang tim menyelesaikan, pantau
A16: 10 | B16: Arahan baru dari kantor pusat tanpa detail | C16: A: bereaksi emosional, menegur di depan umum · B: ambil alih dan kerjakan sendiri | D16: C: menunda, tunggu masalah hilang, tidak eskalasi | E16: D: akui, cari akar, tetapkan tindakan · E: beri ruang tim menyelesaikan, pantau
A18: Game 3 · Priority Poker — kartu aktivitas, twist, dan kunci
A19: No | B19: Kartu aktivitas | C19: Level awal (kunci) | D19: Kartu twist → level akhir
A20: 1 | B20: Komplain nasabah prioritas via call center | C20: P2 | D20: Komplain ternyata viral di media sosial → P1
A21: 2 | B21: Laporan kepatuhan bulanan | C21: P2 | D21: Regulator meminta pukul 12.00 hari ini → P1
A22: 3 | B22: Transaksi abnormal di rekening nasabah | C22: P2 | D22: Ternyata dilakukan staf internal → P1, eskalasi anti-fraud
A23: 4 | B23: Review target bisnis bulanan | C23: P2 | D23: Tidak berubah (tetap P2)
A24: 5 | B24: Coaching staf baru | C24: P3→P2 | D24: Staf baru akan pegang counter sendiri besok → P2
A25: 6 | B25: Undangan rapat koordinasi rutin | C25: P4 | D25: Agenda tidak jelas → tetap P4 / tolak
A26: 7 | B26: Approval kredit dengan dokumen lengkap | C26: P2 | D26: Nasabah ancam pindah bank → P1 bila SLA terlewat
A27: 8 | B27: Grup WhatsApp ramai diskusi umum | C27: P4 | D27: Tetap P4 — batch 2× sehari
A29: Game 4 · Calendar Tetris — kartu jadwal & disrupsi (disrupsi dibuka setelah kalender pertama jadi)
A30: Jenis | B30: Kartu
A31: Fixed | B31: Rapat komite kredit Selasa 09.00–11.00
A32: Fixed | B32: Kunjungan nasabah korporasi Rabu 14.00
A33: Deadline | B33: Laporan kepatuhan Kamis 12.00
A34: Task | B34: Analisis 3 berkas kredit (3 jam)
A35: Task | B35: Coaching 2 staf (2 × 45 menit)
A36: Task | B36: Approval transaksi harian (30 menit/hari)
A37: Request | B37: Management minta paparan kinerja Jumat
A38: Focus | B38: Deep work: rencana strategi cabang (2 jam)
A39: Disrupsi 1 | B39: System down Rabu pagi 2 jam
A40: Disrupsi 2 | B40: Satu staf absen Kamis
A41: Disrupsi 3 | B41: Urgent customer datang Selasa siang
A42: Disrupsi 4 | B42: Regulator request data Jumat pagi
A44: Game 5 · Delegation Relay — amplop instruksi leader
A45: Bagian | B45: Isi
A46: Tugas | B46: Siapkan paket presentasi 'Rencana perbaikan layanan cabang' dalam 20 menit: (1) ringkasan 5 komplain teratas, (2) 3 opsi perbaikan dengan biaya, (3) timeline 4 minggu, (4) satu poster A3 untuk banking hall.
A47: Aturan | B47: Leader dilarang menulis/menggambar. Leader hanya boleh menjelaskan, bertanya, dan memeriksa di checkpoint.
A48: Observer cek | B48: What · Why · Expected outcome · Authority · Boundary · Deadline · Checkpoint · Evidence (centang yang disampaikan leader)
A50: Game 6 · Fact or Fiction — kartu pernyataan
A51: No | B51: Pernyataan | C51: Kunci zona | D51: Data tambahan (dibuka trainer)
A52: 1 | B52: Cabang gagal capai target karena staf malas | C52: Assumption | D52: Kunjungan nasabah turun; 2 RM cuti panjang
A53: 2 | B53: Nasabah ini aman karena sudah 15 tahun | C53: Assumption | D53: Pola transaksi berubah drastis 3 bulan terakhir
A54: 3 | B54: Complaint naik karena aplikasi baru | C54: Unknown | D54: Kenaikan juga terjadi di kanal non-aplikasi
A55: 4 | B55: NPL naik karena ekonomi | C55: Assumption | D55: Kenaikan terkonsentrasi pada satu produk dan satu periode pencairan
A56: 5 | B56: Funding cabang turun 8% dibanding bulan lalu (laporan core banking) | C56: Fact | D56: Data tervalidasi dari sistem
A57: 6 | B57: Nasabah muda tidak suka datang ke cabang | C57: Opinion | D57: Data kunjungan per usia belum pernah dianalisis
A59: Game 7 · Detective Room — 12 evidence card (TAT kredit naik 40%)
A60: No | B60: Topik pertanyaan | C60: Evidence | D60: Kategori (trainer)
A61: 1 | B61: Volume aplikasi | C61: Volume naik tipis (±5%), tidak sebanding kenaikan TAT 40% | D61: Relevan
A62: 2 | B62: Waktu per tahap | C62: Tahap verifikasi dokumen paling lama | D62: Kunci
A63: 3 | B63: Kapasitas tim | C63: Satu analis senior pindah unit 2 bulan lalu | D63: Kunci
A64: 4 | B64: Perubahan kebijakan | C64: Checklist dokumen baru berlaku bulan lalu | D64: Kunci
A65: 5 | B65: Data rework | C65: Banyak berkas dikembalikan karena dokumen kurang | D65: Kunci
A66: 6 | B66: Segmen | C66: Kenaikan TAT terbesar pada kredit produktif | D66: Relevan
A67: 7 | B67: Sistem | C67: Tidak ada downtime signifikan di LOS | D67: Pengecoh
A68: 8 | B68: Appraisal | C68: SLA appraiser eksternal stabil | D68: Pengecoh
A69: 9 | B69: Komite | C69: Jadwal komite tidak berubah | D69: Pengecoh
A70: 10 | B70: Kepuasan RM | C70: RM mengeluh harus mengulang permintaan dokumen | D70: Relevan
A71: 11 | B71: Sosialisasi | C71: Checklist baru tidak disosialisasikan ke nasabah/RM | D71: Kunci
A72: 12 | B72: Benchmark | C72: Cabang lain dengan analis lengkap TAT naik hanya 10% | D72: Relevan
A73: Kunci: bottleneck di verifikasi dokumen akibat checklist baru tanpa sosialisasi + berkurangnya satu analis senior. Bukan semata kenaikan volume.
A75: Game 8 · Root Cause Race — data pendukung (complaint naik 40%)
A76: Data | B76: Isi
A77: Per kategori | B77: Keluhan 'proses lama' naik 70%; kategori lain stabil
A78: Per kanal | B78: Kenaikan di cabang dan call center, bukan hanya aplikasi
A79: Per bulan | B79: Kenaikan mulai setelah jam layanan teller dikurangi
A80: Per produk | B80: Konsentrasi pada pembukaan rekening dan update data
A81: Proses | B81: Antrean CS rata-rata 35 menit (sebelumnya 15)
A82: People | B82: Dua CS dipindah ke unit funding
A84: Game 9 · Bias Trap — kartu keputusan
A85: No | B85: Kartu | C85: Bias (kunci) | D85: Better question (kunci)
A86: 1 | B86: Nasabah VIP sudah lama menjadi nasabah | C86: Halo effect | D86: Apa yang berubah pada kondisi usahanya sekarang?
A87: 2 | B87: Direktur menyukai opsi A | C87: Authority | D87: Bagaimana A dibanding B dan C pada kriteria yang sama?
A88: 3 | B88: Produk ini sukses tahun lalu | C88: Recency / status quo | D88: Asumsi apa yang membuatnya sukses, masih berlaku?
A89: 4 | B89: Semua kompetitor menggunakan sistem ini | C89: Bandwagon / groupthink | D89: Masalah apa yang mau diselesaikan sistem ini?
A90: 5 | B90: Kita sudah keluar Rp 2 M, lanjutkan saja | C90: Sunk cost | D90: Jika mulai dari nol hari ini, apakah kita akan memilih ini?
A91: 6 | B91: Pengajuan limit Rp 10 M, kita tawar jadi 8 M | C91: Anchoring | D91: Berapa limit yang didukung arus kas, terlepas dari angka awal?
A93: Game 11 · 60-Second Boardroom — kartu kasus
A94: Kasus | B94: Brief
A95: Kasus A | B95: Komplain layanan naik 40% di 3 cabang; rekomendasikan langkah 30 hari.
A96: Kasus B | B96: Pipeline kredit UMKM turun 25%; pilih antara promosi atau perbaikan proses.
A97: Kasus C | B97: Audit finding overdue 4 bulan; minta tambahan sumber daya ke Direksi.
A99: War Room — kartu kondisi awal
A100: No | B100: Kondisi
A101: 1 | B101: Business target hanya 82%
A102: 2 | B102: NPL meningkat
A103: 3 | B103: Customer complaint naik
A104: 4 | B104: Audit finding overdue
A105: 5 | B105: Regulatory deadline mendekat
A106: 6 | B106: System instability
A107: 7 | B107: Two employees resign
A108: 8 | B108: Project digitalisasi terlambat
A109: 9 | B109: Fraud alert muncul
A110: 10 | B110: Top customer mengancam pindah
...

Sheet 25 Evaluasi Training
A1: Training Effectiveness Measurement · Kirkpatrick L1–L4
A2: Ringkasan bukti efektivitas training. L1 diisi akhir Day 2; L2 dari test; L3 dari follow-up D30; L4 dari impact metrics.
A3: Legenda: sel kuning = diisi peserta/trainer (teks biru); sel putih/abu = otomatis (rumus) atau panduan.
A5: Level | B5: Yang diukur | C5: Instrumen | D5: Sumber data | E5: Hasil
A6: L1 Reaction | B6: Relevansi, keterlibatan, kegunaan | C6: Kuesioner 1–5 (di bawah) | D6: Akhir Day 2 | E6: =IFERROR(AVERAGE(D16:D23),"")
A7: L2 Learning | B7: Pemahaman framework | C7: Pre/Post Test | D7: Sheet 19b | E7: =IFERROR('19b Test Scoring'!H59,"")
A8: L3 Behavior | B8: Perubahan perilaku kerja | C8: 30-Day Plan + Manager Follow-up | D8: Sheet 20, 21
A9: L4 Results | B9: Dampak ke metrik kerja | C9: Before vs After | D9: Sheet 22 | E9: ='22 Impact Metrics'!G16 -> 0 / 0
A11: Catatan: L2 menampilkan gain rata-rata (Post − Pre). L3 diisi % peserta dengan status 'On track' pada D30.
A14: Kuesioner L1 (rata-rata kelas, skala 1–5)
A15: No | B15: Pernyataan | D15: Rata-rata
A16: 1 | B16: Materi relevan dengan pekerjaan saya
A17: 2 | B17: Game dan simulasi membantu saya memahami konsep
A18: 3 | B18: Saya tahu apa yang akan saya lakukan berbeda besok
A19: 4 | B19: Framework mudah diterapkan di unit saya
A20: 5 | B20: Fasilitator mendorong saya berpikir, bukan sekadar mendengar
A21: 6 | B21: Porsi teori vs praktik seimbang
A22: 7 | B22: Toolkit siap dipakai
A23: 8 | B23: Saya akan merekomendasikan training ini
